{"0": "a1a1", "1": "a1b1", "2": "a1c1", "3": "a1d1", "4": "a1e1", "5": "a1f1", "6": "a1g1", "7": "a1h1", "8": "a1a2", "9": "a1b2", "10": "a1c2", "11": "a1d2", "12": "a1e2", "13": "a1f2", "14": "a1g2", "15": "a1h2", "16": "a1a3", "17": "a1b3", "18": "a1c3", "19": "a1d3", "20": "a1e3", "21": "a1f3", "22": "a1g3", "23": "a1h3", "24": "a1a4", "25": "a1b4", "26": "a1c4", "27": "a1d4", "28": "a1e4", "29": "a1f4", "30": "a1g4", "31": "a1h4", "32": "a1a5", "33": "a1b5", "34": "a1c5", "35": "a1d5", "36": "a1e5", "37": "a1f5", "38": "a1g5", "39": "a1h5", "40": "a1a6", "41": "a1b6", "42": "a1c6", "43": "a1d6", "44": "a1e6", "45": "a1f6", "46": "a1g6", "47": "a1h6", "48": "a1a7", "49": "a1b7", "50": "a1c7", "51": "a1d7", "52": "a1e7", "53": "a1f7", "54": "a1g7", "55": "a1h7", "56": "a1a8", "57": "a1b8", "58": "a1c8", "59": "a1d8", "60": "a1e8", "61": "a1f8", "62": "a1g8", "63": "a1h8", "64": "b1a1", "65": "b1b1", "66": "b1c1", "67": "b1d1", "68": "b1e1", "69": "b1f1", "70": "b1g1", "71": "b1h1", "72": "b1a2", "73": "b1b2", "74": "b1c2", "75": "b1d2", "76": "b1e2", "77": "b1f2", "78": "b1g2", "79": "b1h2", "80": "b1a3", "81": "b1b3", "82": "b1c3", "83": "b1d3", "84": "b1e3", "85": "b1f3", "86": "b1g3", "87": "b1h3", "88": "b1a4", "89": "b1b4", "90": "b1c4", "91": "b1d4", "92": "b1e4", "93": "b1f4", "94": "b1g4", "95": "b1h4", "96": "b1a5", "97": "b1b5", "98": "b1c5", "99": "b1d5", "100": "b1e5", "101": "b1f5", "102": "b1g5", "103": "b1h5", "104": "b1a6", "105": "b1b6", "106": "b1c6", "107": "b1d6", "108": "b1e6", "109": "b1f6", "110": "b1g6", "111": "b1h6", "112": "b1a7", "113": "b1b7", "114": "b1c7", "115": "b1d7", "116": "b1e7", "117": "b1f7", "118": "b1g7", "119": "b1h7", "120": "b1a8", "121": "b1b8", "122": "b1c8", "123": "b1d8", "124": "b1e8", "125": "b1f8", "126": "b1g8", "127": "b1h8", "128": "c1a1", "129": "c1b1", "130": "c1c1", "131": "c1d1", "132": "c1e1", "133": "c1f1", "134": "c1g1", "135": "c1h1", "136": "c1a2", "137": "c1b2", "138": "c1c2", "139": "c1d2", "140": "c1e2", "141": "c1f2", "142": "c1g2", "143": "c1h2", "144": "c1a3", "145": "c1b3", "146": "c1c3", "147": "c1d3", "148": "c1e3", "149": "c1f3", "150": "c1g3", "151": "c1h3", "152": "c1a4", "153": "c1b4", "154": "c1c4", "155": "c1d4", "156": "c1e4", "157": "c1f4", "158": "c1g4", "159": "c1h4", "160": "c1a5", "161": "c1b5", "162": "c1c5", "163": "c1d5", "164": "c1e5", "165": "c1f5", "166": "c1g5", "167": "c1h5", "168": "c1a6", "169": "c1b6", "170": "c1c6", "171": "c1d6", "172": "c1e6", "173": "c1f6", "174": "c1g6", "175": "c1h6", "176": "c1a7", "177": "c1b7", "178": "c1c7", "179": "c1d7", "180": "c1e7", "181": "c1f7", "182": "c1g7", "183": "c1h7", "184": "c1a8", "185": "c1b8", "186": "c1c8", "187": "c1d8", "188": "c1e8", "189": "c1f8", "190": "c1g8", "191": "c1h8", "192": "d1a1", "193": "d1b1", "194": "d1c1", "195": "d1d1", "196": "d1e1", "197": "d1f1", "198": "d1g1", "199": "d1h1", "200": "d1a2", "201": "d1b2", "202": "d1c2", "203": "d1d2", "204": "d1e2", "205": "d1f2", "206": "d1g2", "207": "d1h2", "208": "d1a3", "209": "d1b3", "210": "d1c3", "211": "d1d3", "212": "d1e3", "213": "d1f3", "214": "d1g3", "215": "d1h3", "216": "d1a4", "217": "d1b4", "218": "d1c4", "219": "d1d4", "220": "d1e4", "221": "d1f4", "222": "d1g4", "223": "d1h4", "224": "d1a5", "225": "d1b5", "226": "d1c5", "227": "d1d5", "228": "d1e5", "229": "d1f5", "230": "d1g5", "231": "d1h5", "232": "d1a6", "233": "d1b6", "234": "d1c6", "235": "d1d6", "236": "d1e6", "237": "d1f6", "238": "d1g6", "239": "d1h6", "240": "d1a7", "241": "d1b7", "242": "d1c7", "243": "d1d7", "244": "d1e7", "245": "d1f7", "246": "d1g7", "247": "d1h7", "248": "d1a8", "249": "d1b8", "250": "d1c8", "251": "d1d8", "252": "d1e8", "253": "d1f8", "254": "d1g8", "255": "d1h8", "256": "e1a1", "257": "e1b1", "258": "e1c1", "259": "e1d1", "260": "e1e1", "261": "e1f1", "262": "e1g1", "263": "e1h1", "264": "e1a2", "265": "e1b2", "266": "e1c2", "267": "e1d2", "268": "e1e2", "269": "e1f2", "270": "e1g2", "271": "e1h2", "272": "e1a3", "273": "e1b3", "274": "e1c3", "275": "e1d3", "276": "e1e3", "277": "e1f3", "278": "e1g3", "279": "e1h3", "280": "e1a4", "281": "e1b4", "282": "e1c4", "283": "e1d4", "284": "e1e4", "285": "e1f4", "286": "e1g4", "287": "e1h4", "288": "e1a5", "289": "e1b5", "290": "e1c5", "291": "e1d5", "292": "e1e5", "293": "e1f5", "294": "e1g5", "295": "e1h5", "296": "e1a6", "297": "e1b6", "298": "e1c6", "299": "e1d6", "300": "e1e6", "301": "e1f6", "302": "e1g6", "303": "e1h6", "304": "e1a7", "305": "e1b7", "306": "e1c7", "307": "e1d7", "308": "e1e7", "309": "e1f7", "310": "e1g7", "311": "e1h7", "312": "e1a8", "313": "e1b8", "314": "e1c8", "315": "e1d8", "316": "e1e8", "317": "e1f8", "318": "e1g8", "319": "e1h8", "320": "f1a1", "321": "f1b1", "322": "f1c1", "323": "f1d1", "324": "f1e1", "325": "f1f1", "326": "f1g1", "327": "f1h1", "328": "f1a2", "329": "f1b2", "330": "f1c2", "331": "f1d2", "332": "f1e2", "333": "f1f2", "334": "f1g2", "335": "f1h2", "336": "f1a3", "337": "f1b3", "338": "f1c3", "339": "f1d3", "340": "f1e3", "341": "f1f3", "342": "f1g3", "343": "f1h3", "344": "f1a4", "345": "f1b4", "346": "f1c4", "347": "f1d4", "348": "f1e4", "349": "f1f4", "350": "f1g4", "351": "f1h4", "352": "f1a5", "353": "f1b5", "354": "f1c5", "355": "f1d5", "356": "f1e5", "357": "f1f5", "358": "f1g5", "359": "f1h5", "360": "f1a6", "361": "f1b6", "362": "f1c6", "363": "f1d6", "364": "f1e6", "365": "f1f6", "366": "f1g6", "367": "f1h6", "368": "f1a7", "369": "f1b7", "370": "f1c7", "371": "f1d7", "372": "f1e7", "373": "f1f7", "374": "f1g7", "375": "f1h7", "376": "f1a8", "377": "f1b8", "378": "f1c8", "379": "f1d8", "380": "f1e8", "381": "f1f8", "382": "f1g8", "383": "f1h8", "384": "g1a1", "385": "g1b1", "386": "g1c1", "387": "g1d1", "388": "g1e1", "389": "g1f1", "390": "g1g1", "391": "g1h1", "392": "g1a2", "393": "g1b2", "394": "g1c2", "395": "g1d2", "396": "g1e2", "397": "g1f2", "398": "g1g2", "399": "g1h2", "400": "g1a3", "401": "g1b3", "402": "g1c3", "403": "g1d3", "404": "g1e3", "405": "g1f3", "406": "g1g3", "407": "g1h3", "408": "g1a4", "409": "g1b4", "410": "g1c4", "411": "g1d4", "412": "g1e4", "413": "g1f4", "414": "g1g4", "415": "g1h4", "416": "g1a5", "417": "g1b5", "418": "g1c5", "419": "g1d5", "420": "g1e5", "421": "g1f5", "422": "g1g5", "423": "g1h5", "424": "g1a6", "425": "g1b6", "426": "g1c6", "427": "g1d6", "428": "g1e6", "429": "g1f6", "430": "g1g6", "431": "g1h6", "432": "g1a7", "433": "g1b7", "434": "g1c7", "435": "g1d7", "436": "g1e7", "437": "g1f7", "438": "g1g7", "439": "g1h7", "440": "g1a8", "441": "g1b8", "442": "g1c8", "443": "g1d8", "444": "g1e8", "445": "g1f8", "446": "g1g8", "447": "g1h8", "448": "h1a1", "449": "h1b1", "450": "h1c1", "451": "h1d1", "452": "h1e1", "453": "h1f1", "454": "h1g1", "455": "h1h1", "456": "h1a2", "457": "h1b2", "458": "h1c2", "459": "h1d2", "460": "h1e2", "461": "h1f2", "462": "h1g2", "463": "h1h2", "464": "h1a3", "465": "h1b3", "466": "h1c3", "467": "h1d3", "468": "h1e3", "469": "h1f3", "470": "h1g3", "471": "h1h3", "472": "h1a4", "473": "h1b4", "474": "h1c4", "475": "h1d4", "476": "h1e4", "477": "h1f4", "478": "h1g4", "479": "h1h4", "480": "h1a5", "481": "h1b5", "482": "h1c5", "483": "h1d5", "484": "h1e5", "485": "h1f5", "486": "h1g5", "487": "h1h5", "488": "h1a6", "489": "h1b6", "490": "h1c6", "491": "h1d6", "492": "h1e6", "493": "h1f6", "494": "h1g6", "495": "h1h6", "496": "h1a7", "497": "h1b7", "498": "h1c7", "499": "h1d7", "500": "h1e7", "501": "h1f7", "502": "h1g7", "503": "h1h7", "504": "h1a8", "505": "h1b8", "506": "h1c8", "507": "h1d8", "508": "h1e8", "509": "h1f8", "510": "h1g8", "511": "h1h8", "512": "a2a1", "513": "a2b1", "514": "a2c1", "515": "a2d1", "516": "a2e1", "517": "a2f1", "518": "a2g1", "519": "a2h1", "520": "a2a2", "521": "a2b2", "522": "a2c2", "523": "a2d2", "524": "a2e2", "525": "a2f2", "526": "a2g2", "527": "a2h2", "528": "a2a3", "529": "a2b3", "530": "a2c3", "531": "a2d3", "532": "a2e3", "533": "a2f3", "534": "a2g3", "535": "a2h3", "536": "a2a4", "537": "a2b4", "538": "a2c4", "539": "a2d4", "540": "a2e4", "541": "a2f4", "542": "a2g4", "543": "a2h4", "544": "a2a5", "545": "a2b5", "546": "a2c5", "547": "a2d5", "548": "a2e5", "549": "a2f5", "550": "a2g5", "551": "a2h5", "552": "a2a6", "553": "a2b6", "554": "a2c6", "555": "a2d6", "556": "a2e6", "557": "a2f6", "558": "a2g6", "559": "a2h6", "560": "a2a7", "561": "a2b7", "562": "a2c7", "563": "a2d7", "564": "a2e7", "565": "a2f7", "566": "a2g7", "567": "a2h7", "568": "a2a8", "569": "a2b8", "570": "a2c8", "571": "a2d8", "572": "a2e8", "573": "a2f8", "574": "a2g8", "575": "a2h8", "576": "b2a1", "577": "b2b1", "578": "b2c1", "579": "b2d1", "580": "b2e1", "581": "b2f1", "582": "b2g1", "583": "b2h1", "584": "b2a2", "585": "b2b2", "586": "b2c2", "587": "b2d2", "588": "b2e2", "589": "b2f2", "590": "b2g2", "591": "b2h2", "592": "b2a3", "593": "b2b3", "594": "b2c3", "595": "b2d3", "596": "b2e3", "597": "b2f3", "598": "b2g3", "599": "b2h3", "600": "b2a4", "601": "b2b4", "602": "b2c4", "603": "b2d4", "604": "b2e4", "605": "b2f4", "606": "b2g4", "607": "b2h4", "608": "b2a5", "609": "b2b5", "610": "b2c5", "611": "b2d5", "612": "b2e5", "613": "b2f5", "614": "b2g5", "615": "b2h5", "616": "b2a6", "617": "b2b6", "618": "b2c6", "619": "b2d6", "620": "b2e6", "621": "b2f6", "622": "b2g6", "623": "b2h6", "624": "b2a7", "625": "b2b7", "626": "b2c7", "627": "b2d7", "628": "b2e7", "629": "b2f7", "630": "b2g7", "631": "b2h7", "632": "b2a8", "633": "b2b8", "634": "b2c8", "635": "b2d8", "636": "b2e8", "637": "b2f8", "638": "b2g8", "639": "b2h8", "640": "c2a1", "641": "c2b1", "642": "c2c1", "643": "c2d1", "644": "c2e1", "645": "c2f1", "646": "c2g1", "647": "c2h1", "648": "c2a2", "649": "c2b2", "650": "c2c2", "651": "c2d2", "652": "c2e2", "653": "c2f2", "654": "c2g2", "655": "c2h2", "656": "c2a3", "657": "c2b3", "658": "c2c3", "659": "c2d3", "660": "c2e3", "661": "c2f3", "662": "c2g3", "663": "c2h3", "664": "c2a4", "665": "c2b4", "666": "c2c4", "667": "c2d4", "668": "c2e4", "669": "c2f4", "670": "c2g4", "671": "c2h4", "672": "c2a5", "673": "c2b5", "674": "c2c5", "675": "c2d5", "676": "c2e5", "677": "c2f5", "678": "c2g5", "679": "c2h5", "680": "c2a6", "681": "c2b6", "682": "c2c6", "683": "c2d6", "684": "c2e6", "685": "c2f6", "686": "c2g6", "687": "c2h6", "688": "c2a7", "689": "c2b7", "690": "c2c7", "691": "c2d7", "692": "c2e7", "693": "c2f7", "694": "c2g7", "695": "c2h7", "696": "c2a8", "697": "c2b8", "698": "c2c8", "699": "c2d8", "700": "c2e8", "701": "c2f8", "702": "c2g8", "703": "c2h8", "704": "d2a1", "705": "d2b1", "706": "d2c1", "707": "d2d1", "708": "d2e1", "709": "d2f1", "710": "d2g1", "711": "d2h1", "712": "d2a2", "713": "d2b2", "714": "d2c2", "715": "d2d2", "716": "d2e2", "717": "d2f2", "718": "d2g2", "719": "d2h2", "720": "d2a3", "721": "d2b3", "722": "d2c3", "723": "d2d3", "724": "d2e3", "725": "d2f3", "726": "d2g3", "727": "d2h3", "728": "d2a4", "729": "d2b4", "730": "d2c4", "731": "d2d4", "732": "d2e4", "733": "d2f4", "734": "d2g4", "735": "d2h4", "736": "d2a5", "737": "d2b5", "738": "d2c5", "739": "d2d5", "740": "d2e5", "741": "d2f5", "742": "d2g5", "743": "d2h5", "744": "d2a6", "745": "d2b6", "746": "d2c6", "747": "d2d6", "748": "d2e6", "749": "d2f6", "750": "d2g6", "751": "d2h6", "752": "d2a7", "753": "d2b7", "754": "d2c7", "755": "d2d7", "756": "d2e7", "757": "d2f7", "758": "d2g7", "759": "d2h7", "760": "d2a8", "761": "d2b8", "762": "d2c8", "763": "d2d8", "764": "d2e8", "765": "d2f8", "766": "d2g8", "767": "d2h8", "768": "e2a1", "769": "e2b1", "770": "e2c1", "771": "e2d1", "772": "e2e1", "773": "e2f1", "774": "e2g1", "775": "e2h1", "776": "e2a2", "777": "e2b2", "778": "e2c2", "779": "e2d2", "780": "e2e2", "781": "e2f2", "782": "e2g2", "783": "e2h2", "784": "e2a3", "785": "e2b3", "786": "e2c3", "787": "e2d3", "788": "e2e3", "789": "e2f3", "790": "e2g3", "791": "e2h3", "792": "e2a4", "793": "e2b4", "794": "e2c4", "795": "e2d4", "796": "e2e4", "797": "e2f4", "798": "e2g4", "799": "e2h4", "800": "e2a5", "801": "e2b5", "802": "e2c5", "803": "e2d5", "804": "e2e5", "805": "e2f5", "806": "e2g5", "807": "e2h5", "808": "e2a6", "809": "e2b6", "810": "e2c6", "811": "e2d6", "812": "e2e6", "813": "e2f6", "814": "e2g6", "815": "e2h6", "816": "e2a7", "817": "e2b7", "818": "e2c7", "819": "e2d7", "820": "e2e7", "821": "e2f7", "822": "e2g7", "823": "e2h7", "824": "e2a8", "825": "e2b8", "826": "e2c8", "827": "e2d8", "828": "e2e8", "829": "e2f8", "830": "e2g8", "831": "e2h8", "832": "f2a1", "833": "f2b1", "834": "f2c1", "835": "f2d1", "836": "f2e1", "837": "f2f1", "838": "f2g1", "839": "f2h1", "840": "f2a2", "841": "f2b2", "842": "f2c2", "843": "f2d2", "844": "f2e2", "845": "f2f2", "846": "f2g2", "847": "f2h2", "848": "f2a3", "849": "f2b3", "850": "f2c3", "851": "f2d3", "852": "f2e3", "853": "f2f3", "854": "f2g3", "855": "f2h3", "856": "f2a4", "857": "f2b4", "858": "f2c4", "859": "f2d4", "860": "f2e4", "861": "f2f4", "862": "f2g4", "863": "f2h4", "864": "f2a5", "865": "f2b5", "866": "f2c5", "867": "f2d5", "868": "f2e5", "869": "f2f5", "870": "f2g5", "871": "f2h5", "872": "f2a6", "873": "f2b6", "874": "f2c6", "875": "f2d6", "876": "f2e6", "877": "f2f6", "878": "f2g6", "879": "f2h6", "880": "f2a7", "881": "f2b7", "882": "f2c7", "883": "f2d7", "884": "f2e7", "885": "f2f7", "886": "f2g7", "887": "f2h7", "888": "f2a8", "889": "f2b8", "890": "f2c8", "891": "f2d8", "892": "f2e8", "893": "f2f8", "894": "f2g8", "895": "f2h8", "896": "g2a1", "897": "g2b1", "898": "g2c1", "899": "g2d1", "900": "g2e1", "901": "g2f1", "902": "g2g1", "903": "g2h1", "904": "g2a2", "905": "g2b2", "906": "g2c2", "907": "g2d2", "908": "g2e2", "909": "g2f2", "910": "g2g2", "911": "g2h2", "912": "g2a3", "913": "g2b3", "914": "g2c3", "915": "g2d3", "916": "g2e3", "917": "g2f3", "918": "g2g3", "919": "g2h3", "920": "g2a4", "921": "g2b4", "922": "g2c4", "923": "g2d4", "924": "g2e4", "925": "g2f4", "926": "g2g4", "927": "g2h4", "928": "g2a5", "929": "g2b5", "930": "g2c5", "931": "g2d5", "932": "g2e5", "933": "g2f5", "934": "g2g5", "935": "g2h5", "936": "g2a6", "937": "g2b6", "938": "g2c6", "939": "g2d6", "940": "g2e6", "941": "g2f6", "942": "g2g6", "943": "g2h6", "944": "g2a7", "945": "g2b7", "946": "g2c7", "947": "g2d7", "948": "g2e7", "949": "g2f7", "950": "g2g7", "951": "g2h7", "952": "g2a8", "953": "g2b8", "954": "g2c8", "955": "g2d8", "956": "g2e8", "957": "g2f8", "958": "g2g8", "959": "g2h8", "960": "h2a1", "961": "h2b1", "962": "h2c1", "963": "h2d1", "964": "h2e1", "965": "h2f1", "966": "h2g1", "967": "h2h1", "968": "h2a2", "969": "h2b2", "970": "h2c2", "971": "h2d2", "972": "h2e2", "973": "h2f2", "974": "h2g2", "975": "h2h2", "976": "h2a3", "977": "h2b3", "978": "h2c3", "979": "h2d3", "980": "h2e3", "981": "h2f3", "982": "h2g3", "983": "h2h3", "984": "h2a4", "985": "h2b4", "986": "h2c4", "987": "h2d4", "988": "h2e4", "989": "h2f4", "990": "h2g4", "991": "h2h4", "992": "h2a5", "993": "h2b5", "994": "h2c5", "995": "h2d5", "996": "h2e5", "997": "h2f5", "998": "h2g5", "999": "h2h5", "1000": "h2a6", "1001": "h2b6", "1002": "h2c6", "1003": "h2d6", "1004": "h2e6", "1005": "h2f6", "1006": "h2g6", "1007": "h2h6", "1008": "h2a7", "1009": "h2b7", "1010": "h2c7", "1011": "h2d7", "1012": "h2e7", "1013": "h2f7", "1014": "h2g7", "1015": "h2h7", "1016": "h2a8", "1017": "h2b8", "1018": "h2c8", "1019": "h2d8", "1020": "h2e8", "1021": "h2f8", "1022": "h2g8", "1023": "h2h8", "1024": "a3a1", "1025": "a3b1", "1026": "a3c1", "1027": "a3d1", "1028": "a3e1", "1029": "a3f1", "1030": "a3g1", "1031": "a3h1", "1032": "a3a2", "1033": "a3b2", "1034": "a3c2", "1035": "a3d2", "1036": "a3e2", "1037": "a3f2", "1038": "a3g2", "1039": "a3h2", "1040": "a3a3", "1041": "a3b3", "1042": "a3c3", "1043": "a3d3", "1044": "a3e3", "1045": "a3f3", "1046": "a3g3", "1047": "a3h3", "1048": "a3a4", "1049": "a3b4", "1050": "a3c4", "1051": "a3d4", "1052": "a3e4", "1053": "a3f4", "1054": "a3g4", "1055": "a3h4", "1056": "a3a5", "1057": "a3b5", "1058": "a3c5", "1059": "a3d5", "1060": "a3e5", "1061": "a3f5", "1062": "a3g5", "1063": "a3h5", "1064": "a3a6", "1065": "a3b6", "1066": "a3c6", "1067": "a3d6", "1068": "a3e6", "1069": "a3f6", "1070": "a3g6", "1071": "a3h6", "1072": "a3a7", "1073": "a3b7", "1074": "a3c7", "1075": "a3d7", "1076": "a3e7", "1077": "a3f7", "1078": "a3g7", "1079": "a3h7", "1080": "a3a8", "1081": "a3b8", "1082": "a3c8", "1083": "a3d8", "1084": "a3e8", "1085": "a3f8", "1086": "a3g8", "1087": "a3h8", "1088": "b3a1", "1089": "b3b1", "1090": "b3c1", "1091": "b3d1", "1092": "b3e1", "1093": "b3f1", "1094": "b3g1", "1095": "b3h1", "1096": "b3a2", "1097": "b3b2", "1098": "b3c2", "1099": "b3d2", "1100": "b3e2", "1101": "b3f2", "1102": "b3g2", "1103": "b3h2", "1104": "b3a3", "1105": "b3b3", "1106": "b3c3", "1107": "b3d3", "1108": "b3e3", "1109": "b3f3", "1110": "b3g3", "1111": "b3h3", "1112": "b3a4", "1113": "b3b4", "1114": "b3c4", "1115": "b3d4", "1116": "b3e4", "1117": "b3f4", "1118": "b3g4", "1119": "b3h4", "1120": "b3a5", "1121": "b3b5", "1122": "b3c5", "1123": "b3d5", "1124": "b3e5", "1125": "b3f5", "1126": "b3g5", "1127": "b3h5", "1128": "b3a6", "1129": "b3b6", "1130": "b3c6", "1131": "b3d6", "1132": "b3e6", "1133": "b3f6", "1134": "b3g6", "1135": "b3h6", "1136": "b3a7", "1137": "b3b7", "1138": "b3c7", "1139": "b3d7", "1140": "b3e7", "1141": "b3f7", "1142": "b3g7", "1143": "b3h7", "1144": "b3a8", "1145": "b3b8", "1146": "b3c8", "1147": "b3d8", "1148": "b3e8", "1149": "b3f8", "1150": "b3g8", "1151": "b3h8", "1152": "c3a1", "1153": "c3b1", "1154": "c3c1", "1155": "c3d1", "1156": "c3e1", "1157": "c3f1", "1158": "c3g1", "1159": "c3h1", "1160": "c3a2", "1161": "c3b2", "1162": "c3c2", "1163": "c3d2", "1164": "c3e2", "1165": "c3f2", "1166": "c3g2", "1167": "c3h2", "1168": "c3a3", "1169": "c3b3", "1170": "c3c3", "1171": "c3d3", "1172": "c3e3", "1173": "c3f3", "1174": "c3g3", "1175": "c3h3", "1176": "c3a4", "1177": "c3b4", "1178": "c3c4", "1179": "c3d4", "1180": "c3e4", "1181": "c3f4", "1182": "c3g4", "1183": "c3h4", "1184": "c3a5", "1185": "c3b5", "1186": "c3c5", "1187": "c3d5", "1188": "c3e5", "1189": "c3f5", "1190": "c3g5", "1191": "c3h5", "1192": "c3a6", "1193": "c3b6", "1194": "c3c6", "1195": "c3d6", "1196": "c3e6", "1197": "c3f6", "1198": "c3g6", "1199": "c3h6", "1200": "c3a7", "1201": "c3b7", "1202": "c3c7", "1203": "c3d7", "1204": "c3e7", "1205": "c3f7", "1206": "c3g7", "1207": "c3h7", "1208": "c3a8", "1209": "c3b8", "1210": "c3c8", "1211": "c3d8", "1212": "c3e8", "1213": "c3f8", "1214": "c3g8", "1215": "c3h8", "1216": "d3a1", "1217": "d3b1", "1218": "d3c1", "1219": "d3d1", "1220": "d3e1", "1221": "d3f1", "1222": "d3g1", "1223": "d3h1", "1224": "d3a2", "1225": "d3b2", "1226": "d3c2", "1227": "d3d2", "1228": "d3e2", "1229": "d3f2", "1230": "d3g2", "1231": "d3h2", "1232": "d3a3", "1233": "d3b3", "1234": "d3c3", "1235": "d3d3", "1236": "d3e3", "1237": "d3f3", "1238": "d3g3", "1239": "d3h3", "1240": "d3a4", "1241": "d3b4", "1242": "d3c4", "1243": "d3d4", "1244": "d3e4", "1245": "d3f4", "1246": "d3g4", "1247": "d3h4", "1248": "d3a5", "1249": "d3b5", "1250": "d3c5", "1251": "d3d5", "1252": "d3e5", "1253": "d3f5", "1254": "d3g5", "1255": "d3h5", "1256": "d3a6", "1257": "d3b6", "1258": "d3c6", "1259": "d3d6", "1260": "d3e6", "1261": "d3f6", "1262": "d3g6", "1263": "d3h6", "1264": "d3a7", "1265": "d3b7", "1266": "d3c7", "1267": "d3d7", "1268": "d3e7", "1269": "d3f7", "1270": "d3g7", "1271": "d3h7", "1272": "d3a8", "1273": "d3b8", "1274": "d3c8", "1275": "d3d8", "1276": "d3e8", "1277": "d3f8", "1278": "d3g8", "1279": "d3h8", "1280": "e3a1", "1281": "e3b1", "1282": "e3c1", "1283": "e3d1", "1284": "e3e1", "1285": "e3f1", "1286": "e3g1", "1287": "e3h1", "1288": "e3a2", "1289": "e3b2", "1290": "e3c2", "1291": "e3d2", "1292": "e3e2", "1293": "e3f2", "1294": "e3g2", "1295": "e3h2", "1296": "e3a3", "1297": "e3b3", "1298": "e3c3", "1299": "e3d3", "1300": "e3e3", "1301": "e3f3", "1302": "e3g3", "1303": "e3h3", "1304": "e3a4", "1305": "e3b4", "1306": "e3c4", "1307": "e3d4", "1308": "e3e4", "1309": "e3f4", "1310": "e3g4", "1311": "e3h4", "1312": "e3a5", "1313": "e3b5", "1314": "e3c5", "1315": "e3d5", "1316": "e3e5", "1317": "e3f5", "1318": "e3g5", "1319": "e3h5", "1320": "e3a6", "1321": "e3b6", "1322": "e3c6", "1323": "e3d6", "1324": "e3e6", "1325": "e3f6", "1326": "e3g6", "1327": "e3h6", "1328": "e3a7", "1329": "e3b7", "1330": "e3c7", "1331": "e3d7", "1332": "e3e7", "1333": "e3f7", "1334": "e3g7", "1335": "e3h7", "1336": "e3a8", "1337": "e3b8", "1338": "e3c8", "1339": "e3d8", "1340": "e3e8", "1341": "e3f8", "1342": "e3g8", "1343": "e3h8", "1344": "f3a1", "1345": "f3b1", "1346": "f3c1", "1347": "f3d1", "1348": "f3e1", "1349": "f3f1", "1350": "f3g1", "1351": "f3h1", "1352": "f3a2", "1353": "f3b2", "1354": "f3c2", "1355": "f3d2", "1356": "f3e2", "1357": "f3f2", "1358": "f3g2", "1359": "f3h2", "1360": "f3a3", "1361": "f3b3", "1362": "f3c3", "1363": "f3d3", "1364": "f3e3", "1365": "f3f3", "1366": "f3g3", "1367": "f3h3", "1368": "f3a4", "1369": "f3b4", "1370": "f3c4", "1371": "f3d4", "1372": "f3e4", "1373": "f3f4", "1374": "f3g4", "1375": "f3h4", "1376": "f3a5", "1377": "f3b5", "1378": "f3c5", "1379": "f3d5", "1380": "f3e5", "1381": "f3f5", "1382": "f3g5", "1383": "f3h5", "1384": "f3a6", "1385": "f3b6", "1386": "f3c6", "1387": "f3d6", "1388": "f3e6", "1389": "f3f6", "1390": "f3g6", "1391": "f3h6", "1392": "f3a7", "1393": "f3b7", "1394": "f3c7", "1395": "f3d7", "1396": "f3e7", "1397": "f3f7", "1398": "f3g7", "1399": "f3h7", "1400": "f3a8", "1401": "f3b8", "1402": "f3c8", "1403": "f3d8", "1404": "f3e8", "1405": "f3f8", "1406": "f3g8", "1407": "f3h8", "1408": "g3a1", "1409": "g3b1", "1410": "g3c1", "1411": "g3d1", "1412": "g3e1", "1413": "g3f1", "1414": "g3g1", "1415": "g3h1", "1416": "g3a2", "1417": "g3b2", "1418": "g3c2", "1419": "g3d2", "1420": "g3e2", "1421": "g3f2", "1422": "g3g2", "1423": "g3h2", "1424": "g3a3", "1425": "g3b3", "1426": "g3c3", "1427": "g3d3", "1428": "g3e3", "1429": "g3f3", "1430": "g3g3", "1431": "g3h3", "1432": "g3a4", "1433": "g3b4", "1434": "g3c4", "1435": "g3d4", "1436": "g3e4", "1437": "g3f4", "1438": "g3g4", "1439": "g3h4", "1440": "g3a5", "1441": "g3b5", "1442": "g3c5", "1443": "g3d5", "1444": "g3e5", "1445": "g3f5", "1446": "g3g5", "1447": "g3h5", "1448": "g3a6", "1449": "g3b6", "1450": "g3c6", "1451": "g3d6", "1452": "g3e6", "1453": "g3f6", "1454": "g3g6", "1455": "g3h6", "1456": "g3a7", "1457": "g3b7", "1458": "g3c7", "1459": "g3d7", "1460": "g3e7", "1461": "g3f7", "1462": "g3g7", "1463": "g3h7", "1464": "g3a8", "1465": "g3b8", "1466": "g3c8", "1467": "g3d8", "1468": "g3e8", "1469": "g3f8", "1470": "g3g8", "1471": "g3h8", "1472": "h3a1", "1473": "h3b1", "1474": "h3c1", "1475": "h3d1", "1476": "h3e1", "1477": "h3f1", "1478": "h3g1", "1479": "h3h1", "1480": "h3a2", "1481": "h3b2", "1482": "h3c2", "1483": "h3d2", "1484": "h3e2", "1485": "h3f2", "1486": "h3g2", "1487": "h3h2", "1488": "h3a3", "1489": "h3b3", "1490": "h3c3", "1491": "h3d3", "1492": "h3e3", "1493": "h3f3", "1494": "h3g3", "1495": "h3h3", "1496": "h3a4", "1497": "h3b4", "1498": "h3c4", "1499": "h3d4", "1500": "h3e4", "1501": "h3f4", "1502": "h3g4", "1503": "h3h4", "1504": "h3a5", "1505": "h3b5", "1506": "h3c5", "1507": "h3d5", "1508": "h3e5", "1509": "h3f5", "1510": "h3g5", "1511": "h3h5", "1512": "h3a6", "1513": "h3b6", "1514": "h3c6", "1515": "h3d6", "1516": "h3e6", "1517": "h3f6", "1518": "h3g6", "1519": "h3h6", "1520": "h3a7", "1521": "h3b7", "1522": "h3c7", "1523": "h3d7", "1524": "h3e7", "1525": "h3f7", "1526": "h3g7", "1527": "h3h7", "1528": "h3a8", "1529": "h3b8", "1530": "h3c8", "1531": "h3d8", "1532": "h3e8", "1533": "h3f8", "1534": "h3g8", "1535": "h3h8", "1536": "a4a1", "1537": "a4b1", "1538": "a4c1", "1539": "a4d1", "1540": "a4e1", "1541": "a4f1", "1542": "a4g1", "1543": "a4h1", "1544": "a4a2", "1545": "a4b2", "1546": "a4c2", "1547": "a4d2", "1548": "a4e2", "1549": "a4f2", "1550": "a4g2", "1551": "a4h2", "1552": "a4a3", "1553": "a4b3", "1554": "a4c3", "1555": "a4d3", "1556": "a4e3", "1557": "a4f3", "1558": "a4g3", "1559": "a4h3", "1560": "a4a4", "1561": "a4b4", "1562": "a4c4", "1563": "a4d4", "1564": "a4e4", "1565": "a4f4", "1566": "a4g4", "1567": "a4h4", "1568": "a4a5", "1569": "a4b5", "1570": "a4c5", "1571": "a4d5", "1572": "a4e5", "1573": "a4f5", "1574": "a4g5", "1575": "a4h5", "1576": "a4a6", "1577": "a4b6", "1578": "a4c6", "1579": "a4d6", "1580": "a4e6", "1581": "a4f6", "1582": "a4g6", "1583": "a4h6", "1584": "a4a7", "1585": "a4b7", "1586": "a4c7", "1587": "a4d7", "1588": "a4e7", "1589": "a4f7", "1590": "a4g7", "1591": "a4h7", "1592": "a4a8", "1593": "a4b8", "1594": "a4c8", "1595": "a4d8", "1596": "a4e8", "1597": "a4f8", "1598": "a4g8", "1599": "a4h8", "1600": "b4a1", "1601": "b4b1", "1602": "b4c1", "1603": "b4d1", "1604": "b4e1", "1605": "b4f1", "1606": "b4g1", "1607": "b4h1", "1608": "b4a2", "1609": "b4b2", "1610": "b4c2", "1611": "b4d2", "1612": "b4e2", "1613": "b4f2", "1614": "b4g2", "1615": "b4h2", "1616": "b4a3", "1617": "b4b3", "1618": "b4c3", "1619": "b4d3", "1620": "b4e3", "1621": "b4f3", "1622": "b4g3", "1623": "b4h3", "1624": "b4a4", "1625": "b4b4", "1626": "b4c4", "1627": "b4d4", "1628": "b4e4", "1629": "b4f4", "1630": "b4g4", "1631": "b4h4", "1632": "b4a5", "1633": "b4b5", "1634": "b4c5", "1635": "b4d5", "1636": "b4e5", "1637": "b4f5", "1638": "b4g5", "1639": "b4h5", "1640": "b4a6", "1641": "b4b6", "1642": "b4c6", "1643": "b4d6", "1644": "b4e6", "1645": "b4f6", "1646": "b4g6", "1647": "b4h6", "1648": "b4a7", "1649": "b4b7", "1650": "b4c7", "1651": "b4d7", "1652": "b4e7", "1653": "b4f7", "1654": "b4g7", "1655": "b4h7", "1656": "b4a8", "1657": "b4b8", "1658": "b4c8", "1659": "b4d8", "1660": "b4e8", "1661": "b4f8", "1662": "b4g8", "1663": "b4h8", "1664": "c4a1", "1665": "c4b1", "1666": "c4c1", "1667": "c4d1", "1668": "c4e1", "1669": "c4f1", "1670": "c4g1", "1671": "c4h1", "1672": "c4a2", "1673": "c4b2", "1674": "c4c2", "1675": "c4d2", "1676": "c4e2", "1677": "c4f2", "1678": "c4g2", "1679": "c4h2", "1680": "c4a3", "1681": "c4b3", "1682": "c4c3", "1683": "c4d3", "1684": "c4e3", "1685": "c4f3", "1686": "c4g3", "1687": "c4h3", "1688": "c4a4", "1689": "c4b4", "1690": "c4c4", "1691": "c4d4", "1692": "c4e4", "1693": "c4f4", "1694": "c4g4", "1695": "c4h4", "1696": "c4a5", "1697": "c4b5", "1698": "c4c5", "1699": "c4d5", "1700": "c4e5", "1701": "c4f5", "1702": "c4g5", "1703": "c4h5", "1704": "c4a6", "1705": "c4b6", "1706": "c4c6", "1707": "c4d6", "1708": "c4e6", "1709": "c4f6", "1710": "c4g6", "1711": "c4h6", "1712": "c4a7", "1713": "c4b7", "1714": "c4c7", "1715": "c4d7", "1716": "c4e7", "1717": "c4f7", "1718": "c4g7", "1719": "c4h7", "1720": "c4a8", "1721": "c4b8", "1722": "c4c8", "1723": "c4d8", "1724": "c4e8", "1725": "c4f8", "1726": "c4g8", "1727": "c4h8", "1728": "d4a1", "1729": "d4b1", "1730": "d4c1", "1731": "d4d1", "1732": "d4e1", "1733": "d4f1", "1734": "d4g1", "1735": "d4h1", "1736": "d4a2", "1737": "d4b2", "1738": "d4c2", "1739": "d4d2", "1740": "d4e2", "1741": "d4f2", "1742": "d4g2", "1743": "d4h2", "1744": "d4a3", "1745": "d4b3", "1746": "d4c3", "1747": "d4d3", "1748": "d4e3", "1749": "d4f3", "1750": "d4g3", "1751": "d4h3", "1752": "d4a4", "1753": "d4b4", "1754": "d4c4", "1755": "d4d4", "1756": "d4e4", "1757": "d4f4", "1758": "d4g4", "1759": "d4h4", "1760": "d4a5", "1761": "d4b5", "1762": "d4c5", "1763": "d4d5", "1764": "d4e5", "1765": "d4f5", "1766": "d4g5", "1767": "d4h5", "1768": "d4a6", "1769": "d4b6", "1770": "d4c6", "1771": "d4d6", "1772": "d4e6", "1773": "d4f6", "1774": "d4g6", "1775": "d4h6", "1776": "d4a7", "1777": "d4b7", "1778": "d4c7", "1779": "d4d7", "1780": "d4e7", "1781": "d4f7", "1782": "d4g7", "1783": "d4h7", "1784": "d4a8", "1785": "d4b8", "1786": "d4c8", "1787": "d4d8", "1788": "d4e8", "1789": "d4f8", "1790": "d4g8", "1791": "d4h8", "1792": "e4a1", "1793": "e4b1", "1794": "e4c1", "1795": "e4d1", "1796": "e4e1", "1797": "e4f1", "1798": "e4g1", "1799": "e4h1", "1800": "e4a2", "1801": "e4b2", "1802": "e4c2", "1803": "e4d2", "1804": "e4e2", "1805": "e4f2", "1806": "e4g2", "1807": "e4h2", "1808": "e4a3", "1809": "e4b3", "1810": "e4c3", "1811": "e4d3", "1812": "e4e3", "1813": "e4f3", "1814": "e4g3", "1815": "e4h3", "1816": "e4a4", "1817": "e4b4", "1818": "e4c4", "1819": "e4d4", "1820": "e4e4", "1821": "e4f4", "1822": "e4g4", "1823": "e4h4", "1824": "e4a5", "1825": "e4b5", "1826": "e4c5", "1827": "e4d5", "1828": "e4e5", "1829": "e4f5", "1830": "e4g5", "1831": "e4h5", "1832": "e4a6", "1833": "e4b6", "1834": "e4c6", "1835": "e4d6", "1836": "e4e6", "1837": "e4f6", "1838": "e4g6", "1839": "e4h6", "1840": "e4a7", "1841": "e4b7", "1842": "e4c7", "1843": "e4d7", "1844": "e4e7", "1845": "e4f7", "1846": "e4g7", "1847": "e4h7", "1848": "e4a8", "1849": "e4b8", "1850": "e4c8", "1851": "e4d8", "1852": "e4e8", "1853": "e4f8", "1854": "e4g8", "1855": "e4h8", "1856": "f4a1", "1857": "f4b1", "1858": "f4c1", "1859": "f4d1", "1860": "f4e1", "1861": "f4f1", "1862": "f4g1", "1863": "f4h1", "1864": "f4a2", "1865": "f4b2", "1866": "f4c2", "1867": "f4d2", "1868": "f4e2", "1869": "f4f2", "1870": "f4g2", "1871": "f4h2", "1872": "f4a3", "1873": "f4b3", "1874": "f4c3", "1875": "f4d3", "1876": "f4e3", "1877": "f4f3", "1878": "f4g3", "1879": "f4h3", "1880": "f4a4", "1881": "f4b4", "1882": "f4c4", "1883": "f4d4", "1884": "f4e4", "1885": "f4f4", "1886": "f4g4", "1887": "f4h4", "1888": "f4a5", "1889": "f4b5", "1890": "f4c5", "1891": "f4d5", "1892": "f4e5", "1893": "f4f5", "1894": "f4g5", "1895": "f4h5", "1896": "f4a6", "1897": "f4b6", "1898": "f4c6", "1899": "f4d6", "1900": "f4e6", "1901": "f4f6", "1902": "f4g6", "1903": "f4h6", "1904": "f4a7", "1905": "f4b7", "1906": "f4c7", "1907": "f4d7", "1908": "f4e7", "1909": "f4f7", "1910": "f4g7", "1911": "f4h7", "1912": "f4a8", "1913": "f4b8", "1914": "f4c8", "1915": "f4d8", "1916": "f4e8", "1917": "f4f8", "1918": "f4g8", "1919": "f4h8", "1920": "g4a1", "1921": "g4b1", "1922": "g4c1", "1923": "g4d1", "1924": "g4e1", "1925": "g4f1", "1926": "g4g1", "1927": "g4h1", "1928": "g4a2", "1929": "g4b2", "1930": "g4c2", "1931": "g4d2", "1932": "g4e2", "1933": "g4f2", "1934": "g4g2", "1935": "g4h2", "1936": "g4a3", "1937": "g4b3", "1938": "g4c3", "1939": "g4d3", "1940": "g4e3", "1941": "g4f3", "1942": "g4g3", "1943": "g4h3", "1944": "g4a4", "1945": "g4b4", "1946": "g4c4", "1947": "g4d4", "1948": "g4e4", "1949": "g4f4", "1950": "g4g4", "1951": "g4h4", "1952": "g4a5", "1953": "g4b5", "1954": "g4c5", "1955": "g4d5", "1956": "g4e5", "1957": "g4f5", "1958": "g4g5", "1959": "g4h5", "1960": "g4a6", "1961": "g4b6", "1962": "g4c6", "1963": "g4d6", "1964": "g4e6", "1965": "g4f6", "1966": "g4g6", "1967": "g4h6", "1968": "g4a7", "1969": "g4b7", "1970": "g4c7", "1971": "g4d7", "1972": "g4e7", "1973": "g4f7", "1974": "g4g7", "1975": "g4h7", "1976": "g4a8", "1977": "g4b8", "1978": "g4c8", "1979": "g4d8", "1980": "g4e8", "1981": "g4f8", "1982": "g4g8", "1983": "g4h8", "1984": "h4a1", "1985": "h4b1", "1986": "h4c1", "1987": "h4d1", "1988": "h4e1", "1989": "h4f1", "1990": "h4g1", "1991": "h4h1", "1992": "h4a2", "1993": "h4b2", "1994": "h4c2", "1995": "h4d2", "1996": "h4e2", "1997": "h4f2", "1998": "h4g2", "1999": "h4h2", "2000": "h4a3", "2001": "h4b3", "2002": "h4c3", "2003": "h4d3", "2004": "h4e3", "2005": "h4f3", "2006": "h4g3", "2007": "h4h3", "2008": "h4a4", "2009": "h4b4", "2010": "h4c4", "2011": "h4d4", "2012": "h4e4", "2013": "h4f4", "2014": "h4g4", "2015": "h4h4", "2016": "h4a5", "2017": "h4b5", "2018": "h4c5", "2019": "h4d5", "2020": "h4e5", "2021": "h4f5", "2022": "h4g5", "2023": "h4h5", "2024": "h4a6", "2025": "h4b6", "2026": "h4c6", "2027": "h4d6", "2028": "h4e6", "2029": "h4f6", "2030": "h4g6", "2031": "h4h6", "2032": "h4a7", "2033": "h4b7", "2034": "h4c7", "2035": "h4d7", "2036": "h4e7", "2037": "h4f7", "2038": "h4g7", "2039": "h4h7", "2040": "h4a8", "2041": "h4b8", "2042": "h4c8", "2043": "h4d8", "2044": "h4e8", "2045": "h4f8", "2046": "h4g8", "2047": "h4h8", "2048": "a5a1", "2049": "a5b1", "2050": "a5c1", "2051": "a5d1", "2052": "a5e1", "2053": "a5f1", "2054": "a5g1", "2055": "a5h1", "2056": "a5a2", "2057": "a5b2", "2058": "a5c2", "2059": "a5d2", "2060": "a5e2", "2061": "a5f2", "2062": "a5g2", "2063": "a5h2", "2064": "a5a3", "2065": "a5b3", "2066": "a5c3", "2067": "a5d3", "2068": "a5e3", "2069": "a5f3", "2070": "a5g3", "2071": "a5h3", "2072": "a5a4", "2073": "a5b4", "2074": "a5c4", "2075": "a5d4", "2076": "a5e4", "2077": "a5f4", "2078": "a5g4", "2079": "a5h4", "2080": "a5a5", "2081": "a5b5", "2082": "a5c5", "2083": "a5d5", "2084": "a5e5", "2085": "a5f5", "2086": "a5g5", "2087": "a5h5", "2088": "a5a6", "2089": "a5b6", "2090": "a5c6", "2091": "a5d6", "2092": "a5e6", "2093": "a5f6", "2094": "a5g6", "2095": "a5h6", "2096": "a5a7", "2097": "a5b7", "2098": "a5c7", "2099": "a5d7", "2100": "a5e7", "2101": "a5f7", "2102": "a5g7", "2103": "a5h7", "2104": "a5a8", "2105": "a5b8", "2106": "a5c8", "2107": "a5d8", "2108": "a5e8", "2109": "a5f8", "2110": "a5g8", "2111": "a5h8", "2112": "b5a1", "2113": "b5b1", "2114": "b5c1", "2115": "b5d1", "2116": "b5e1", "2117": "b5f1", "2118": "b5g1", "2119": "b5h1", "2120": "b5a2", "2121": "b5b2", "2122": "b5c2", "2123": "b5d2", "2124": "b5e2", "2125": "b5f2", "2126": "b5g2", "2127": "b5h2", "2128": "b5a3", "2129": "b5b3", "2130": "b5c3", "2131": "b5d3", "2132": "b5e3", "2133": "b5f3", "2134": "b5g3", "2135": "b5h3", "2136": "b5a4", "2137": "b5b4", "2138": "b5c4", "2139": "b5d4", "2140": "b5e4", "2141": "b5f4", "2142": "b5g4", "2143": "b5h4", "2144": "b5a5", "2145": "b5b5", "2146": "b5c5", "2147": "b5d5", "2148": "b5e5", "2149": "b5f5", "2150": "b5g5", "2151": "b5h5", "2152": "b5a6", "2153": "b5b6", "2154": "b5c6", "2155": "b5d6", "2156": "b5e6", "2157": "b5f6", "2158": "b5g6", "2159": "b5h6", "2160": "b5a7", "2161": "b5b7", "2162": "b5c7", "2163": "b5d7", "2164": "b5e7", "2165": "b5f7", "2166": "b5g7", "2167": "b5h7", "2168": "b5a8", "2169": "b5b8", "2170": "b5c8", "2171": "b5d8", "2172": "b5e8", "2173": "b5f8", "2174": "b5g8", "2175": "b5h8", "2176": "c5a1", "2177": "c5b1", "2178": "c5c1", "2179": "c5d1", "2180": "c5e1", "2181": "c5f1", "2182": "c5g1", "2183": "c5h1", "2184": "c5a2", "2185": "c5b2", "2186": "c5c2", "2187": "c5d2", "2188": "c5e2", "2189": "c5f2", "2190": "c5g2", "2191": "c5h2", "2192": "c5a3", "2193": "c5b3", "2194": "c5c3", "2195": "c5d3", "2196": "c5e3", "2197": "c5f3", "2198": "c5g3", "2199": "c5h3", "2200": "c5a4", "2201": "c5b4", "2202": "c5c4", "2203": "c5d4", "2204": "c5e4", "2205": "c5f4", "2206": "c5g4", "2207": "c5h4", "2208": "c5a5", "2209": "c5b5", "2210": "c5c5", "2211": "c5d5", "2212": "c5e5", "2213": "c5f5", "2214": "c5g5", "2215": "c5h5", "2216": "c5a6", "2217": "c5b6", "2218": "c5c6", "2219": "c5d6", "2220": "c5e6", "2221": "c5f6", "2222": "c5g6", "2223": "c5h6", "2224": "c5a7", "2225": "c5b7", "2226": "c5c7", "2227": "c5d7", "2228": "c5e7", "2229": "c5f7", "2230": "c5g7", "2231": "c5h7", "2232": "c5a8", "2233": "c5b8", "2234": "c5c8", "2235": "c5d8", "2236": "c5e8", "2237": "c5f8", "2238": "c5g8", "2239": "c5h8", "2240": "d5a1", "2241": "d5b1", "2242": "d5c1", "2243": "d5d1", "2244": "d5e1", "2245": "d5f1", "2246": "d5g1", "2247": "d5h1", "2248": "d5a2", "2249": "d5b2", "2250": "d5c2", "2251": "d5d2", "2252": "d5e2", "2253": "d5f2", "2254": "d5g2", "2255": "d5h2", "2256": "d5a3", "2257": "d5b3", "2258": "d5c3", "2259": "d5d3", "2260": "d5e3", "2261": "d5f3", "2262": "d5g3", "2263": "d5h3", "2264": "d5a4", "2265": "d5b4", "2266": "d5c4", "2267": "d5d4", "2268": "d5e4", "2269": "d5f4", "2270": "d5g4", "2271": "d5h4", "2272": "d5a5", "2273": "d5b5", "2274": "d5c5", "2275": "d5d5", "2276": "d5e5", "2277": "d5f5", "2278": "d5g5", "2279": "d5h5", "2280": "d5a6", "2281": "d5b6", "2282": "d5c6", "2283": "d5d6", "2284": "d5e6", "2285": "d5f6", "2286": "d5g6", "2287": "d5h6", "2288": "d5a7", "2289": "d5b7", "2290": "d5c7", "2291": "d5d7", "2292": "d5e7", "2293": "d5f7", "2294": "d5g7", "2295": "d5h7", "2296": "d5a8", "2297": "d5b8", "2298": "d5c8", "2299": "d5d8", "2300": "d5e8", "2301": "d5f8", "2302": "d5g8", "2303": "d5h8", "2304": "e5a1", "2305": "e5b1", "2306": "e5c1", "2307": "e5d1", "2308": "e5e1", "2309": "e5f1", "2310": "e5g1", "2311": "e5h1", "2312": "e5a2", "2313": "e5b2", "2314": "e5c2", "2315": "e5d2", "2316": "e5e2", "2317": "e5f2", "2318": "e5g2", "2319": "e5h2", "2320": "e5a3", "2321": "e5b3", "2322": "e5c3", "2323": "e5d3", "2324": "e5e3", "2325": "e5f3", "2326": "e5g3", "2327": "e5h3", "2328": "e5a4", "2329": "e5b4", "2330": "e5c4", "2331": "e5d4", "2332": "e5e4", "2333": "e5f4", "2334": "e5g4", "2335": "e5h4", "2336": "e5a5", "2337": "e5b5", "2338": "e5c5", "2339": "e5d5", "2340": "e5e5", "2341": "e5f5", "2342": "e5g5", "2343": "e5h5", "2344": "e5a6", "2345": "e5b6", "2346": "e5c6", "2347": "e5d6", "2348": "e5e6", "2349": "e5f6", "2350": "e5g6", "2351": "e5h6", "2352": "e5a7", "2353": "e5b7", "2354": "e5c7", "2355": "e5d7", "2356": "e5e7", "2357": "e5f7", "2358": "e5g7", "2359": "e5h7", "2360": "e5a8", "2361": "e5b8", "2362": "e5c8", "2363": "e5d8", "2364": "e5e8", "2365": "e5f8", "2366": "e5g8", "2367": "e5h8", "2368": "f5a1", "2369": "f5b1", "2370": "f5c1", "2371": "f5d1", "2372": "f5e1", "2373": "f5f1", "2374": "f5g1", "2375": "f5h1", "2376": "f5a2", "2377": "f5b2", "2378": "f5c2", "2379": "f5d2", "2380": "f5e2", "2381": "f5f2", "2382": "f5g2", "2383": "f5h2", "2384": "f5a3", "2385": "f5b3", "2386": "f5c3", "2387": "f5d3", "2388": "f5e3", "2389": "f5f3", "2390": "f5g3", "2391": "f5h3", "2392": "f5a4", "2393": "f5b4", "2394": "f5c4", "2395": "f5d4", "2396": "f5e4", "2397": "f5f4", "2398": "f5g4", "2399": "f5h4", "2400": "f5a5", "2401": "f5b5", "2402": "f5c5", "2403": "f5d5", "2404": "f5e5", "2405": "f5f5", "2406": "f5g5", "2407": "f5h5", "2408": "f5a6", "2409": "f5b6", "2410": "f5c6", "2411": "f5d6", "2412": "f5e6", "2413": "f5f6", "2414": "f5g6", "2415": "f5h6", "2416": "f5a7", "2417": "f5b7", "2418": "f5c7", "2419": "f5d7", "2420": "f5e7", "2421": "f5f7", "2422": "f5g7", "2423": "f5h7", "2424": "f5a8", "2425": "f5b8", "2426": "f5c8", "2427": "f5d8", "2428": "f5e8", "2429": "f5f8", "2430": "f5g8", "2431": "f5h8", "2432": "g5a1", "2433": "g5b1", "2434": "g5c1", "2435": "g5d1", "2436": "g5e1", "2437": "g5f1", "2438": "g5g1", "2439": "g5h1", "2440": "g5a2", "2441": "g5b2", "2442": "g5c2", "2443": "g5d2", "2444": "g5e2", "2445": "g5f2", "2446": "g5g2", "2447": "g5h2", "2448": "g5a3", "2449": "g5b3", "2450": "g5c3", "2451": "g5d3", "2452": "g5e3", "2453": "g5f3", "2454": "g5g3", "2455": "g5h3", "2456": "g5a4", "2457": "g5b4", "2458": "g5c4", "2459": "g5d4", "2460": "g5e4", "2461": "g5f4", "2462": "g5g4", "2463": "g5h4", "2464": "g5a5", "2465": "g5b5", "2466": "g5c5", "2467": "g5d5", "2468": "g5e5", "2469": "g5f5", "2470": "g5g5", "2471": "g5h5", "2472": "g5a6", "2473": "g5b6", "2474": "g5c6", "2475": "g5d6", "2476": "g5e6", "2477": "g5f6", "2478": "g5g6", "2479": "g5h6", "2480": "g5a7", "2481": "g5b7", "2482": "g5c7", "2483": "g5d7", "2484": "g5e7", "2485": "g5f7", "2486": "g5g7", "2487": "g5h7", "2488": "g5a8", "2489": "g5b8", "2490": "g5c8", "2491": "g5d8", "2492": "g5e8", "2493": "g5f8", "2494": "g5g8", "2495": "g5h8", "2496": "h5a1", "2497": "h5b1", "2498": "h5c1", "2499": "h5d1", "2500": "h5e1", "2501": "h5f1", "2502": "h5g1", "2503": "h5h1", "2504": "h5a2", "2505": "h5b2", "2506": "h5c2", "2507": "h5d2", "2508": "h5e2", "2509": "h5f2", "2510": "h5g2", "2511": "h5h2", "2512": "h5a3", "2513": "h5b3", "2514": "h5c3", "2515": "h5d3", "2516": "h5e3", "2517": "h5f3", "2518": "h5g3", "2519": "h5h3", "2520": "h5a4", "2521": "h5b4", "2522": "h5c4", "2523": "h5d4", "2524": "h5e4", "2525": "h5f4", "2526": "h5g4", "2527": "h5h4", "2528": "h5a5", "2529": "h5b5", "2530": "h5c5", "2531": "h5d5", "2532": "h5e5", "2533": "h5f5", "2534": "h5g5", "2535": "h5h5", "2536": "h5a6", "2537": "h5b6", "2538": "h5c6", "2539": "h5d6", "2540": "h5e6", "2541": "h5f6", "2542": "h5g6", "2543": "h5h6", "2544": "h5a7", "2545": "h5b7", "2546": "h5c7", "2547": "h5d7", "2548": "h5e7", "2549": "h5f7", "2550": "h5g7", "2551": "h5h7", "2552": "h5a8", "2553": "h5b8", "2554": "h5c8", "2555": "h5d8", "2556": "h5e8", "2557": "h5f8", "2558": "h5g8", "2559": "h5h8", "2560": "a6a1", "2561": "a6b1", "2562": "a6c1", "2563": "a6d1", "2564": "a6e1", "2565": "a6f1", "2566": "a6g1", "2567": "a6h1", "2568": "a6a2", "2569": "a6b2", "2570": "a6c2", "2571": "a6d2", "2572": "a6e2", "2573": "a6f2", "2574": "a6g2", "2575": "a6h2", "2576": "a6a3", "2577": "a6b3", "2578": "a6c3", "2579": "a6d3", "2580": "a6e3", "2581": "a6f3", "2582": "a6g3", "2583": "a6h3", "2584": "a6a4", "2585": "a6b4", "2586": "a6c4", "2587": "a6d4", "2588": "a6e4", "2589": "a6f4", "2590": "a6g4", "2591": "a6h4", "2592": "a6a5", "2593": "a6b5", "2594": "a6c5", "2595": "a6d5", "2596": "a6e5", "2597": "a6f5", "2598": "a6g5", "2599": "a6h5", "2600": "a6a6", "2601": "a6b6", "2602": "a6c6", "2603": "a6d6", "2604": "a6e6", "2605": "a6f6", "2606": "a6g6", "2607": "a6h6", "2608": "a6a7", "2609": "a6b7", "2610": "a6c7", "2611": "a6d7", "2612": "a6e7", "2613": "a6f7", "2614": "a6g7", "2615": "a6h7", "2616": "a6a8", "2617": "a6b8", "2618": "a6c8", "2619": "a6d8", "2620": "a6e8", "2621": "a6f8", "2622": "a6g8", "2623": "a6h8", "2624": "b6a1", "2625": "b6b1", "2626": "b6c1", "2627": "b6d1", "2628": "b6e1", "2629": "b6f1", "2630": "b6g1", "2631": "b6h1", "2632": "b6a2", "2633": "b6b2", "2634": "b6c2", "2635": "b6d2", "2636": "b6e2", "2637": "b6f2", "2638": "b6g2", "2639": "b6h2", "2640": "b6a3", "2641": "b6b3", "2642": "b6c3", "2643": "b6d3", "2644": "b6e3", "2645": "b6f3", "2646": "b6g3", "2647": "b6h3", "2648": "b6a4", "2649": "b6b4", "2650": "b6c4", "2651": "b6d4", "2652": "b6e4", "2653": "b6f4", "2654": "b6g4", "2655": "b6h4", "2656": "b6a5", "2657": "b6b5", "2658": "b6c5", "2659": "b6d5", "2660": "b6e5", "2661": "b6f5", "2662": "b6g5", "2663": "b6h5", "2664": "b6a6", "2665": "b6b6", "2666": "b6c6", "2667": "b6d6", "2668": "b6e6", "2669": "b6f6", "2670": "b6g6", "2671": "b6h6", "2672": "b6a7", "2673": "b6b7", "2674": "b6c7", "2675": "b6d7", "2676": "b6e7", "2677": "b6f7", "2678": "b6g7", "2679": "b6h7", "2680": "b6a8", "2681": "b6b8", "2682": "b6c8", "2683": "b6d8", "2684": "b6e8", "2685": "b6f8", "2686": "b6g8", "2687": "b6h8", "2688": "c6a1", "2689": "c6b1", "2690": "c6c1", "2691": "c6d1", "2692": "c6e1", "2693": "c6f1", "2694": "c6g1", "2695": "c6h1", "2696": "c6a2", "2697": "c6b2", "2698": "c6c2", "2699": "c6d2", "2700": "c6e2", "2701": "c6f2", "2702": "c6g2", "2703": "c6h2", "2704": "c6a3", "2705": "c6b3", "2706": "c6c3", "2707": "c6d3", "2708": "c6e3", "2709": "c6f3", "2710": "c6g3", "2711": "c6h3", "2712": "c6a4", "2713": "c6b4", "2714": "c6c4", "2715": "c6d4", "2716": "c6e4", "2717": "c6f4", "2718": "c6g4", "2719": "c6h4", "2720": "c6a5", "2721": "c6b5", "2722": "c6c5", "2723": "c6d5", "2724": "c6e5", "2725": "c6f5", "2726": "c6g5", "2727": "c6h5", "2728": "c6a6", "2729": "c6b6", "2730": "c6c6", "2731": "c6d6", "2732": "c6e6", "2733": "c6f6", "2734": "c6g6", "2735": "c6h6", "2736": "c6a7", "2737": "c6b7", "2738": "c6c7", "2739": "c6d7", "2740": "c6e7", "2741": "c6f7", "2742": "c6g7", "2743": "c6h7", "2744": "c6a8", "2745": "c6b8", "2746": "c6c8", "2747": "c6d8", "2748": "c6e8", "2749": "c6f8", "2750": "c6g8", "2751": "c6h8", "2752": "d6a1", "2753": "d6b1", "2754": "d6c1", "2755": "d6d1", "2756": "d6e1", "2757": "d6f1", "2758": "d6g1", "2759": "d6h1", "2760": "d6a2", "2761": "d6b2", "2762": "d6c2", "2763": "d6d2", "2764": "d6e2", "2765": "d6f2", "2766": "d6g2", "2767": "d6h2", "2768": "d6a3", "2769": "d6b3", "2770": "d6c3", "2771": "d6d3", "2772": "d6e3", "2773": "d6f3", "2774": "d6g3", "2775": "d6h3", "2776": "d6a4", "2777": "d6b4", "2778": "d6c4", "2779": "d6d4", "2780": "d6e4", "2781": "d6f4", "2782": "d6g4", "2783": "d6h4", "2784": "d6a5", "2785": "d6b5", "2786": "d6c5", "2787": "d6d5", "2788": "d6e5", "2789": "d6f5", "2790": "d6g5", "2791": "d6h5", "2792": "d6a6", "2793": "d6b6", "2794": "d6c6", "2795": "d6d6", "2796": "d6e6", "2797": "d6f6", "2798": "d6g6", "2799": "d6h6", "2800": "d6a7", "2801": "d6b7", "2802": "d6c7", "2803": "d6d7", "2804": "d6e7", "2805": "d6f7", "2806": "d6g7", "2807": "d6h7", "2808": "d6a8", "2809": "d6b8", "2810": "d6c8", "2811": "d6d8", "2812": "d6e8", "2813": "d6f8", "2814": "d6g8", "2815": "d6h8", "2816": "e6a1", "2817": "e6b1", "2818": "e6c1", "2819": "e6d1", "2820": "e6e1", "2821": "e6f1", "2822": "e6g1", "2823": "e6h1", "2824": "e6a2", "2825": "e6b2", "2826": "e6c2", "2827": "e6d2", "2828": "e6e2", "2829": "e6f2", "2830": "e6g2", "2831": "e6h2", "2832": "e6a3", "2833": "e6b3", "2834": "e6c3", "2835": "e6d3", "2836": "e6e3", "2837": "e6f3", "2838": "e6g3", "2839": "e6h3", "2840": "e6a4", "2841": "e6b4", "2842": "e6c4", "2843": "e6d4", "2844": "e6e4", "2845": "e6f4", "2846": "e6g4", "2847": "e6h4", "2848": "e6a5", "2849": "e6b5", "2850": "e6c5", "2851": "e6d5", "2852": "e6e5", "2853": "e6f5", "2854": "e6g5", "2855": "e6h5", "2856": "e6a6", "2857": "e6b6", "2858": "e6c6", "2859": "e6d6", "2860": "e6e6", "2861": "e6f6", "2862": "e6g6", "2863": "e6h6", "2864": "e6a7", "2865": "e6b7", "2866": "e6c7", "2867": "e6d7", "2868": "e6e7", "2869": "e6f7", "2870": "e6g7", "2871": "e6h7", "2872": "e6a8", "2873": "e6b8", "2874": "e6c8", "2875": "e6d8", "2876": "e6e8", "2877": "e6f8", "2878": "e6g8", "2879": "e6h8", "2880": "f6a1", "2881": "f6b1", "2882": "f6c1", "2883": "f6d1", "2884": "f6e1", "2885": "f6f1", "2886": "f6g1", "2887": "f6h1", "2888": "f6a2", "2889": "f6b2", "2890": "f6c2", "2891": "f6d2", "2892": "f6e2", "2893": "f6f2", "2894": "f6g2", "2895": "f6h2", "2896": "f6a3", "2897": "f6b3", "2898": "f6c3", "2899": "f6d3", "2900": "f6e3", "2901": "f6f3", "2902": "f6g3", "2903": "f6h3", "2904": "f6a4", "2905": "f6b4", "2906": "f6c4", "2907": "f6d4", "2908": "f6e4", "2909": "f6f4", "2910": "f6g4", "2911": "f6h4", "2912": "f6a5", "2913": "f6b5", "2914": "f6c5", "2915": "f6d5", "2916": "f6e5", "2917": "f6f5", "2918": "f6g5", "2919": "f6h5", "2920": "f6a6", "2921": "f6b6", "2922": "f6c6", "2923": "f6d6", "2924": "f6e6", "2925": "f6f6", "2926": "f6g6", "2927": "f6h6", "2928": "f6a7", "2929": "f6b7", "2930": "f6c7", "2931": "f6d7", "2932": "f6e7", "2933": "f6f7", "2934": "f6g7", "2935": "f6h7", "2936": "f6a8", "2937": "f6b8", "2938": "f6c8", "2939": "f6d8", "2940": "f6e8", "2941": "f6f8", "2942": "f6g8", "2943": "f6h8", "2944": "g6a1", "2945": "g6b1", "2946": "g6c1", "2947": "g6d1", "2948": "g6e1", "2949": "g6f1", "2950": "g6g1", "2951": "g6h1", "2952": "g6a2", "2953": "g6b2", "2954": "g6c2", "2955": "g6d2", "2956": "g6e2", "2957": "g6f2", "2958": "g6g2", "2959": "g6h2", "2960": "g6a3", "2961": "g6b3", "2962": "g6c3", "2963": "g6d3", "2964": "g6e3", "2965": "g6f3", "2966": "g6g3", "2967": "g6h3", "2968": "g6a4", "2969": "g6b4", "2970": "g6c4", "2971": "g6d4", "2972": "g6e4", "2973": "g6f4", "2974": "g6g4", "2975": "g6h4", "2976": "g6a5", "2977": "g6b5", "2978": "g6c5", "2979": "g6d5", "2980": "g6e5", "2981": "g6f5", "2982": "g6g5", "2983": "g6h5", "2984": "g6a6", "2985": "g6b6", "2986": "g6c6", "2987": "g6d6", "2988": "g6e6", "2989": "g6f6", "2990": "g6g6", "2991": "g6h6", "2992": "g6a7", "2993": "g6b7", "2994": "g6c7", "2995": "g6d7", "2996": "g6e7", "2997": "g6f7", "2998": "g6g7", "2999": "g6h7", "3000": "g6a8", "3001": "g6b8", "3002": "g6c8", "3003": "g6d8", "3004": "g6e8", "3005": "g6f8", "3006": "g6g8", "3007": "g6h8", "3008": "h6a1", "3009": "h6b1", "3010": "h6c1", "3011": "h6d1", "3012": "h6e1", "3013": "h6f1", "3014": "h6g1", "3015": "h6h1", "3016": "h6a2", "3017": "h6b2", "3018": "h6c2", "3019": "h6d2", "3020": "h6e2", "3021": "h6f2", "3022": "h6g2", "3023": "h6h2", "3024": "h6a3", "3025": "h6b3", "3026": "h6c3", "3027": "h6d3", "3028": "h6e3", "3029": "h6f3", "3030": "h6g3", "3031": "h6h3", "3032": "h6a4", "3033": "h6b4", "3034": "h6c4", "3035": "h6d4", "3036": "h6e4", "3037": "h6f4", "3038": "h6g4", "3039": "h6h4", "3040": "h6a5", "3041": "h6b5", "3042": "h6c5", "3043": "h6d5", "3044": "h6e5", "3045": "h6f5", "3046": "h6g5", "3047": "h6h5", "3048": "h6a6", "3049": "h6b6", "3050": "h6c6", "3051": "h6d6", "3052": "h6e6", "3053": "h6f6", "3054": "h6g6", "3055": "h6h6", "3056": "h6a7", "3057": "h6b7", "3058": "h6c7", "3059": "h6d7", "3060": "h6e7", "3061": "h6f7", "3062": "h6g7", "3063": "h6h7", "3064": "h6a8", "3065": "h6b8", "3066": "h6c8", "3067": "h6d8", "3068": "h6e8", "3069": "h6f8", "3070": "h6g8", "3071": "h6h8", "3072": "a7a1", "3073": "a7b1", "3074": "a7c1", "3075": "a7d1", "3076": "a7e1", "3077": "a7f1", "3078": "a7g1", "3079": "a7h1", "3080": "a7a2", "3081": "a7b2", "3082": "a7c2", "3083": "a7d2", "3084": "a7e2", "3085": "a7f2", "3086": "a7g2", "3087": "a7h2", "3088": "a7a3", "3089": "a7b3", "3090": "a7c3", "3091": "a7d3", "3092": "a7e3", "3093": "a7f3", "3094": "a7g3", "3095": "a7h3", "3096": "a7a4", "3097": "a7b4", "3098": "a7c4", "3099": "a7d4", "3100": "a7e4", "3101": "a7f4", "3102": "a7g4", "3103": "a7h4", "3104": "a7a5", "3105": "a7b5", "3106": "a7c5", "3107": "a7d5", "3108": "a7e5", "3109": "a7f5", "3110": "a7g5", "3111": "a7h5", "3112": "a7a6", "3113": "a7b6", "3114": "a7c6", "3115": "a7d6", "3116": "a7e6", "3117": "a7f6", "3118": "a7g6", "3119": "a7h6", "3120": "a7a7", "3121": "a7b7", "3122": "a7c7", "3123": "a7d7", "3124": "a7e7", "3125": "a7f7", "3126": "a7g7", "3127": "a7h7", "3128": "a7a8", "3129": "a7b8", "3130": "a7c8", "3131": "a7d8", "3132": "a7e8", "3133": "a7f8", "3134": "a7g8", "3135": "a7h8", "3136": "b7a1", "3137": "b7b1", "3138": "b7c1", "3139": "b7d1", "3140": "b7e1", "3141": "b7f1", "3142": "b7g1", "3143": "b7h1", "3144": "b7a2", "3145": "b7b2", "3146": "b7c2", "3147": "b7d2", "3148": "b7e2", "3149": "b7f2", "3150": "b7g2", "3151": "b7h2", "3152": "b7a3", "3153": "b7b3", "3154": "b7c3", "3155": "b7d3", "3156": "b7e3", "3157": "b7f3", "3158": "b7g3", "3159": "b7h3", "3160": "b7a4", "3161": "b7b4", "3162": "b7c4", "3163": "b7d4", "3164": "b7e4", "3165": "b7f4", "3166": "b7g4", "3167": "b7h4", "3168": "b7a5", "3169": "b7b5", "3170": "b7c5", "3171": "b7d5", "3172": "b7e5", "3173": "b7f5", "3174": "b7g5", "3175": "b7h5", "3176": "b7a6", "3177": "b7b6", "3178": "b7c6", "3179": "b7d6", "3180": "b7e6", "3181": "b7f6", "3182": "b7g6", "3183": "b7h6", "3184": "b7a7", "3185": "b7b7", "3186": "b7c7", "3187": "b7d7", "3188": "b7e7", "3189": "b7f7", "3190": "b7g7", "3191": "b7h7", "3192": "b7a8", "3193": "b7b8", "3194": "b7c8", "3195": "b7d8", "3196": "b7e8", "3197": "b7f8", "3198": "b7g8", "3199": "b7h8", "3200": "c7a1", "3201": "c7b1", "3202": "c7c1", "3203": "c7d1", "3204": "c7e1", "3205": "c7f1", "3206": "c7g1", "3207": "c7h1", "3208": "c7a2", "3209": "c7b2", "3210": "c7c2", "3211": "c7d2", "3212": "c7e2", "3213": "c7f2", "3214": "c7g2", "3215": "c7h2", "3216": "c7a3", "3217": "c7b3", "3218": "c7c3", "3219": "c7d3", "3220": "c7e3", "3221": "c7f3", "3222": "c7g3", "3223": "c7h3", "3224": "c7a4", "3225": "c7b4", "3226": "c7c4", "3227": "c7d4", "3228": "c7e4", "3229": "c7f4", "3230": "c7g4", "3231": "c7h4", "3232": "c7a5", "3233": "c7b5", "3234": "c7c5", "3235": "c7d5", "3236": "c7e5", "3237": "c7f5", "3238": "c7g5", "3239": "c7h5", "3240": "c7a6", "3241": "c7b6", "3242": "c7c6", "3243": "c7d6", "3244": "c7e6", "3245": "c7f6", "3246": "c7g6", "3247": "c7h6", "3248": "c7a7", "3249": "c7b7", "3250": "c7c7", "3251": "c7d7", "3252": "c7e7", "3253": "c7f7", "3254": "c7g7", "3255": "c7h7", "3256": "c7a8", "3257": "c7b8", "3258": "c7c8", "3259": "c7d8", "3260": "c7e8", "3261": "c7f8", "3262": "c7g8", "3263": "c7h8", "3264": "d7a1", "3265": "d7b1", "3266": "d7c1", "3267": "d7d1", "3268": "d7e1", "3269": "d7f1", "3270": "d7g1", "3271": "d7h1", "3272": "d7a2", "3273": "d7b2", "3274": "d7c2", "3275": "d7d2", "3276": "d7e2", "3277": "d7f2", "3278": "d7g2", "3279": "d7h2", "3280": "d7a3", "3281": "d7b3", "3282": "d7c3", "3283": "d7d3", "3284": "d7e3", "3285": "d7f3", "3286": "d7g3", "3287": "d7h3", "3288": "d7a4", "3289": "d7b4", "3290": "d7c4", "3291": "d7d4", "3292": "d7e4", "3293": "d7f4", "3294": "d7g4", "3295": "d7h4", "3296": "d7a5", "3297": "d7b5", "3298": "d7c5", "3299": "d7d5", "3300": "d7e5", "3301": "d7f5", "3302": "d7g5", "3303": "d7h5", "3304": "d7a6", "3305": "d7b6", "3306": "d7c6", "3307": "d7d6", "3308": "d7e6", "3309": "d7f6", "3310": "d7g6", "3311": "d7h6", "3312": "d7a7", "3313": "d7b7", "3314": "d7c7", "3315": "d7d7", "3316": "d7e7", "3317": "d7f7", "3318": "d7g7", "3319": "d7h7", "3320": "d7a8", "3321": "d7b8", "3322": "d7c8", "3323": "d7d8", "3324": "d7e8", "3325": "d7f8", "3326": "d7g8", "3327": "d7h8", "3328": "e7a1", "3329": "e7b1", "3330": "e7c1", "3331": "e7d1", "3332": "e7e1", "3333": "e7f1", "3334": "e7g1", "3335": "e7h1", "3336": "e7a2", "3337": "e7b2", "3338": "e7c2", "3339": "e7d2", "3340": "e7e2", "3341": "e7f2", "3342": "e7g2", "3343": "e7h2", "3344": "e7a3", "3345": "e7b3", "3346": "e7c3", "3347": "e7d3", "3348": "e7e3", "3349": "e7f3", "3350": "e7g3", "3351": "e7h3", "3352": "e7a4", "3353": "e7b4", "3354": "e7c4", "3355": "e7d4", "3356": "e7e4", "3357": "e7f4", "3358": "e7g4", "3359": "e7h4", "3360": "e7a5", "3361": "e7b5", "3362": "e7c5", "3363": "e7d5", "3364": "e7e5", "3365": "e7f5", "3366": "e7g5", "3367": "e7h5", "3368": "e7a6", "3369": "e7b6", "3370": "e7c6", "3371": "e7d6", "3372": "e7e6", "3373": "e7f6", "3374": "e7g6", "3375": "e7h6", "3376": "e7a7", "3377": "e7b7", "3378": "e7c7", "3379": "e7d7", "3380": "e7e7", "3381": "e7f7", "3382": "e7g7", "3383": "e7h7", "3384": "e7a8", "3385": "e7b8", "3386": "e7c8", "3387": "e7d8", "3388": "e7e8", "3389": "e7f8", "3390": "e7g8", "3391": "e7h8", "3392": "f7a1", "3393": "f7b1", "3394": "f7c1", "3395": "f7d1", "3396": "f7e1", "3397": "f7f1", "3398": "f7g1", "3399": "f7h1", "3400": "f7a2", "3401": "f7b2", "3402": "f7c2", "3403": "f7d2", "3404": "f7e2", "3405": "f7f2", "3406": "f7g2", "3407": "f7h2", "3408": "f7a3", "3409": "f7b3", "3410": "f7c3", "3411": "f7d3", "3412": "f7e3", "3413": "f7f3", "3414": "f7g3", "3415": "f7h3", "3416": "f7a4", "3417": "f7b4", "3418": "f7c4", "3419": "f7d4", "3420": "f7e4", "3421": "f7f4", "3422": "f7g4", "3423": "f7h4", "3424": "f7a5", "3425": "f7b5", "3426": "f7c5", "3427": "f7d5", "3428": "f7e5", "3429": "f7f5", "3430": "f7g5", "3431": "f7h5", "3432": "f7a6", "3433": "f7b6", "3434": "f7c6", "3435": "f7d6", "3436": "f7e6", "3437": "f7f6", "3438": "f7g6", "3439": "f7h6", "3440": "f7a7", "3441": "f7b7", "3442": "f7c7", "3443": "f7d7", "3444": "f7e7", "3445": "f7f7", "3446": "f7g7", "3447": "f7h7", "3448": "f7a8", "3449": "f7b8", "3450": "f7c8", "3451": "f7d8", "3452": "f7e8", "3453": "f7f8", "3454": "f7g8", "3455": "f7h8", "3456": "g7a1", "3457": "g7b1", "3458": "g7c1", "3459": "g7d1", "3460": "g7e1", "3461": "g7f1", "3462": "g7g1", "3463": "g7h1", "3464": "g7a2", "3465": "g7b2", "3466": "g7c2", "3467": "g7d2", "3468": "g7e2", "3469": "g7f2", "3470": "g7g2", "3471": "g7h2", "3472": "g7a3", "3473": "g7b3", "3474": "g7c3", "3475": "g7d3", "3476": "g7e3", "3477": "g7f3", "3478": "g7g3", "3479": "g7h3", "3480": "g7a4", "3481": "g7b4", "3482": "g7c4", "3483": "g7d4", "3484": "g7e4", "3485": "g7f4", "3486": "g7g4", "3487": "g7h4", "3488": "g7a5", "3489": "g7b5", "3490": "g7c5", "3491": "g7d5", "3492": "g7e5", "3493": "g7f5", "3494": "g7g5", "3495": "g7h5", "3496": "g7a6", "3497": "g7b6", "3498": "g7c6", "3499": "g7d6", "3500": "g7e6", "3501": "g7f6", "3502": "g7g6", "3503": "g7h6", "3504": "g7a7", "3505": "g7b7", "3506": "g7c7", "3507": "g7d7", "3508": "g7e7", "3509": "g7f7", "3510": "g7g7", "3511": "g7h7", "3512": "g7a8", "3513": "g7b8", "3514": "g7c8", "3515": "g7d8", "3516": "g7e8", "3517": "g7f8", "3518": "g7g8", "3519": "g7h8", "3520": "h7a1", "3521": "h7b1", "3522": "h7c1", "3523": "h7d1", "3524": "h7e1", "3525": "h7f1", "3526": "h7g1", "3527": "h7h1", "3528": "h7a2", "3529": "h7b2", "3530": "h7c2", "3531": "h7d2", "3532": "h7e2", "3533": "h7f2", "3534": "h7g2", "3535": "h7h2", "3536": "h7a3", "3537": "h7b3", "3538": "h7c3", "3539": "h7d3", "3540": "h7e3", "3541": "h7f3", "3542": "h7g3", "3543": "h7h3", "3544": "h7a4", "3545": "h7b4", "3546": "h7c4", "3547": "h7d4", "3548": "h7e4", "3549": "h7f4", "3550": "h7g4", "3551": "h7h4", "3552": "h7a5", "3553": "h7b5", "3554": "h7c5", "3555": "h7d5", "3556": "h7e5", "3557": "h7f5", "3558": "h7g5", "3559": "h7h5", "3560": "h7a6", "3561": "h7b6", "3562": "h7c6", "3563": "h7d6", "3564": "h7e6", "3565": "h7f6", "3566": "h7g6", "3567": "h7h6", "3568": "h7a7", "3569": "h7b7", "3570": "h7c7", "3571": "h7d7", "3572": "h7e7", "3573": "h7f7", "3574": "h7g7", "3575": "h7h7", "3576": "h7a8", "3577": "h7b8", "3578": "h7c8", "3579": "h7d8", "3580": "h7e8", "3581": "h7f8", "3582": "h7g8", "3583": "h7h8", "3584": "a8a1", "3585": "a8b1", "3586": "a8c1", "3587": "a8d1", "3588": "a8e1", "3589": "a8f1", "3590": "a8g1", "3591": "a8h1", "3592": "a8a2", "3593": "a8b2", "3594": "a8c2", "3595": "a8d2", "3596": "a8e2", "3597": "a8f2", "3598": "a8g2", "3599": "a8h2", "3600": "a8a3", "3601": "a8b3", "3602": "a8c3", "3603": "a8d3", "3604": "a8e3", "3605": "a8f3", "3606": "a8g3", "3607": "a8h3", "3608": "a8a4", "3609": "a8b4", "3610": "a8c4", "3611": "a8d4", "3612": "a8e4", "3613": "a8f4", "3614": "a8g4", "3615": "a8h4", "3616": "a8a5", "3617": "a8b5", "3618": "a8c5", "3619": "a8d5", "3620": "a8e5", "3621": "a8f5", "3622": "a8g5", "3623": "a8h5", "3624": "a8a6", "3625": "a8b6", "3626": "a8c6", "3627": "a8d6", "3628": "a8e6", "3629": "a8f6", "3630": "a8g6", "3631": "a8h6", "3632": "a8a7", "3633": "a8b7", "3634": "a8c7", "3635": "a8d7", "3636": "a8e7", "3637": "a8f7", "3638": "a8g7", "3639": "a8h7", "3640": "a8a8", "3641": "a8b8", "3642": "a8c8", "3643": "a8d8", "3644": "a8e8", "3645": "a8f8", "3646": "a8g8", "3647": "a8h8", "3648": "b8a1", "3649": "b8b1", "3650": "b8c1", "3651": "b8d1", "3652": "b8e1", "3653": "b8f1", "3654": "b8g1", "3655": "b8h1", "3656": "b8a2", "3657": "b8b2", "3658": "b8c2", "3659": "b8d2", "3660": "b8e2", "3661": "b8f2", "3662": "b8g2", "3663": "b8h2", "3664": "b8a3", "3665": "b8b3", "3666": "b8c3", "3667": "b8d3", "3668": "b8e3", "3669": "b8f3", "3670": "b8g3", "3671": "b8h3", "3672": "b8a4", "3673": "b8b4", "3674": "b8c4", "3675": "b8d4", "3676": "b8e4", "3677": "b8f4", "3678": "b8g4", "3679": "b8h4", "3680": "b8a5", "3681": "b8b5", "3682": "b8c5", "3683": "b8d5", "3684": "b8e5", "3685": "b8f5", "3686": "b8g5", "3687": "b8h5", "3688": "b8a6", "3689": "b8b6", "3690": "b8c6", "3691": "b8d6", "3692": "b8e6", "3693": "b8f6", "3694": "b8g6", "3695": "b8h6", "3696": "b8a7", "3697": "b8b7", "3698": "b8c7", "3699": "b8d7", "3700": "b8e7", "3701": "b8f7", "3702": "b8g7", "3703": "b8h7", "3704": "b8a8", "3705": "b8b8", "3706": "b8c8", "3707": "b8d8", "3708": "b8e8", "3709": "b8f8", "3710": "b8g8", "3711": "b8h8", "3712": "c8a1", "3713": "c8b1", "3714": "c8c1", "3715": "c8d1", "3716": "c8e1", "3717": "c8f1", "3718": "c8g1", "3719": "c8h1", "3720": "c8a2", "3721": "c8b2", "3722": "c8c2", "3723": "c8d2", "3724": "c8e2", "3725": "c8f2", "3726": "c8g2", "3727": "c8h2", "3728": "c8a3", "3729": "c8b3", "3730": "c8c3", "3731": "c8d3", "3732": "c8e3", "3733": "c8f3", "3734": "c8g3", "3735": "c8h3", "3736": "c8a4", "3737": "c8b4", "3738": "c8c4", "3739": "c8d4", "3740": "c8e4", "3741": "c8f4", "3742": "c8g4", "3743": "c8h4", "3744": "c8a5", "3745": "c8b5", "3746": "c8c5", "3747": "c8d5", "3748": "c8e5", "3749": "c8f5", "3750": "c8g5", "3751": "c8h5", "3752": "c8a6", "3753": "c8b6", "3754": "c8c6", "3755": "c8d6", "3756": "c8e6", "3757": "c8f6", "3758": "c8g6", "3759": "c8h6", "3760": "c8a7", "3761": "c8b7", "3762": "c8c7", "3763": "c8d7", "3764": "c8e7", "3765": "c8f7", "3766": "c8g7", "3767": "c8h7", "3768": "c8a8", "3769": "c8b8", "3770": "c8c8", "3771": "c8d8", "3772": "c8e8", "3773": "c8f8", "3774": "c8g8", "3775": "c8h8", "3776": "d8a1", "3777": "d8b1", "3778": "d8c1", "3779": "d8d1", "3780": "d8e1", "3781": "d8f1", "3782": "d8g1", "3783": "d8h1", "3784": "d8a2", "3785": "d8b2", "3786": "d8c2", "3787": "d8d2", "3788": "d8e2", "3789": "d8f2", "3790": "d8g2", "3791": "d8h2", "3792": "d8a3", "3793": "d8b3", "3794": "d8c3", "3795": "d8d3", "3796": "d8e3", "3797": "d8f3", "3798": "d8g3", "3799": "d8h3", "3800": "d8a4", "3801": "d8b4", "3802": "d8c4", "3803": "d8d4", "3804": "d8e4", "3805": "d8f4", "3806": "d8g4", "3807": "d8h4", "3808": "d8a5", "3809": "d8b5", "3810": "d8c5", "3811": "d8d5", "3812": "d8e5", "3813": "d8f5", "3814": "d8g5", "3815": "d8h5", "3816": "d8a6", "3817": "d8b6", "3818": "d8c6", "3819": "d8d6", "3820": "d8e6", "3821": "d8f6", "3822": "d8g6", "3823": "d8h6", "3824": "d8a7", "3825": "d8b7", "3826": "d8c7", "3827": "d8d7", "3828": "d8e7", "3829": "d8f7", "3830": "d8g7", "3831": "d8h7", "3832": "d8a8", "3833": "d8b8", "3834": "d8c8", "3835": "d8d8", "3836": "d8e8", "3837": "d8f8", "3838": "d8g8", "3839": "d8h8", "3840": "e8a1", "3841": "e8b1", "3842": "e8c1", "3843": "e8d1", "3844": "e8e1", "3845": "e8f1", "3846": "e8g1", "3847": "e8h1", "3848": "e8a2", "3849": "e8b2", "3850": "e8c2", "3851": "e8d2", "3852": "e8e2", "3853": "e8f2", "3854": "e8g2", "3855": "e8h2", "3856": "e8a3", "3857": "e8b3", "3858": "e8c3", "3859": "e8d3", "3860": "e8e3", "3861": "e8f3", "3862": "e8g3", "3863": "e8h3", "3864": "e8a4", "3865": "e8b4", "3866": "e8c4", "3867": "e8d4", "3868": "e8e4", "3869": "e8f4", "3870": "e8g4", "3871": "e8h4", "3872": "e8a5", "3873": "e8b5", "3874": "e8c5", "3875": "e8d5", "3876": "e8e5", "3877": "e8f5", "3878": "e8g5", "3879": "e8h5", "3880": "e8a6", "3881": "e8b6", "3882": "e8c6", "3883": "e8d6", "3884": "e8e6", "3885": "e8f6", "3886": "e8g6", "3887": "e8h6", "3888": "e8a7", "3889": "e8b7", "3890": "e8c7", "3891": "e8d7", "3892": "e8e7", "3893": "e8f7", "3894": "e8g7", "3895": "e8h7", "3896": "e8a8", "3897": "e8b8", "3898": "e8c8", "3899": "e8d8", "3900": "e8e8", "3901": "e8f8", "3902": "e8g8", "3903": "e8h8", "3904": "f8a1", "3905": "f8b1", "3906": "f8c1", "3907": "f8d1", "3908": "f8e1", "3909": "f8f1", "3910": "f8g1", "3911": "f8h1", "3912": "f8a2", "3913": "f8b2", "3914": "f8c2", "3915": "f8d2", "3916": "f8e2", "3917": "f8f2", "3918": "f8g2", "3919": "f8h2", "3920": "f8a3", "3921": "f8b3", "3922": "f8c3", "3923": "f8d3", "3924": "f8e3", "3925": "f8f3", "3926": "f8g3", "3927": "f8h3", "3928": "f8a4", "3929": "f8b4", "3930": "f8c4", "3931": "f8d4", "3932": "f8e4", "3933": "f8f4", "3934": "f8g4", "3935": "f8h4", "3936": "f8a5", "3937": "f8b5", "3938": "f8c5", "3939": "f8d5", "3940": "f8e5", "3941": "f8f5", "3942": "f8g5", "3943": "f8h5", "3944": "f8a6", "3945": "f8b6", "3946": "f8c6", "3947": "f8d6", "3948": "f8e6", "3949": "f8f6", "3950": "f8g6", "3951": "f8h6", "3952": "f8a7", "3953": "f8b7", "3954": "f8c7", "3955": "f8d7", "3956": "f8e7", "3957": "f8f7", "3958": "f8g7", "3959": "f8h7", "3960": "f8a8", "3961": "f8b8", "3962": "f8c8", "3963": "f8d8", "3964": "f8e8", "3965": "f8f8", "3966": "f8g8", "3967": "f8h8", "3968": "g8a1", "3969": "g8b1", "3970": "g8c1", "3971": "g8d1", "3972": "g8e1", "3973": "g8f1", "3974": "g8g1", "3975": "g8h1", "3976": "g8a2", "3977": "g8b2", "3978": "g8c2", "3979": "g8d2", "3980": "g8e2", "3981": "g8f2", "3982": "g8g2", "3983": "g8h2", "3984": "g8a3", "3985": "g8b3", "3986": "g8c3", "3987": "g8d3", "3988": "g8e3", "3989": "g8f3", "3990": "g8g3", "3991": "g8h3", "3992": "g8a4", "3993": "g8b4", "3994": "g8c4", "3995": "g8d4", "3996": "g8e4", "3997": "g8f4", "3998": "g8g4", "3999": "g8h4", "4000": "g8a5", "4001": "g8b5", "4002": "g8c5", "4003": "g8d5", "4004": "g8e5", "4005": "g8f5", "4006": "g8g5", "4007": "g8h5", "4008": "g8a6", "4009": "g8b6", "4010": "g8c6", "4011": "g8d6", "4012": "g8e6", "4013": "g8f6", "4014": "g8g6", "4015": "g8h6", "4016": "g8a7", "4017": "g8b7", "4018": "g8c7", "4019": "g8d7", "4020": "g8e7", "4021": "g8f7", "4022": "g8g7", "4023": "g8h7", "4024": "g8a8", "4025": "g8b8", "4026": "g8c8", "4027": "g8d8", "4028": "g8e8", "4029": "g8f8", "4030": "g8g8", "4031": "g8h8", "4032": "h8a1", "4033": "h8b1", "4034": "h8c1", "4035": "h8d1", "4036": "h8e1", "4037": "h8f1", "4038": "h8g1", "4039": "h8h1", "4040": "h8a2", "4041": "h8b2", "4042": "h8c2", "4043": "h8d2", "4044": "h8e2", "4045": "h8f2", "4046": "h8g2", "4047": "h8h2", "4048": "h8a3", "4049": "h8b3", "4050": "h8c3", "4051": "h8d3", "4052": "h8e3", "4053": "h8f3", "4054": "h8g3", "4055": "h8h3", "4056": "h8a4", "4057": "h8b4", "4058": "h8c4", "4059": "h8d4", "4060": "h8e4", "4061": "h8f4", "4062": "h8g4", "4063": "h8h4", "4064": "h8a5", "4065": "h8b5", "4066": "h8c5", "4067": "h8d5", "4068": "h8e5", "4069": "h8f5", "4070": "h8g5", "4071": "h8h5", "4072": "h8a6", "4073": "h8b6", "4074": "h8c6", "4075": "h8d6", "4076": "h8e6", "4077": "h8f6", "4078": "h8g6", "4079": "h8h6", "4080": "h8a7", "4081": "h8b7", "4082": "h8c7", "4083": "h8d7", "4084": "h8e7", "4085": "h8f7", "4086": "h8g7", "4087": "h8h7", "4088": "h8a8", "4089": "h8b8", "4090": "h8c8", "4091": "h8d8", "4092": "h8e8", "4093": "h8f8", "4094": "h8g8", "4095": "h8h8", "4096": "a7a8q", "4097": "a7a8r", "4098": "a7a8b", "4099": "a7a8n", "4100": "a7b8q", "4101": "a7b8r", "4102": "a7b8b", "4103": "a7b8n", "4104": "a7c8q", "4105": "a7c8r", "4106": "a7c8b", "4107": "a7c8n", "4108": "a7d8q", "4109": "a7d8r", "4110": "a7d8b", "4111": "a7d8n", "4112": "a7e8q", "4113": "a7e8r", "4114": "a7e8b", "4115": "a7e8n", "4116": "a7f8q", "4117": "a7f8r", "4118": "a7f8b", "4119": "a7f8n", "4120": "a7g8q", "4121": "a7g8r", "4122": "a7g8b", "4123": "a7g8n", "4124": "a7h8q", "4125": "a7h8r", "4126": "a7h8b", "4127": "a7h8n", "4128": "b7a8q", "4129": "b7a8r", "4130": "b7a8b", "4131": "b7a8n", "4132": "b7b8q", "4133": "b7b8r", "4134": "b7b8b", "4135": "b7b8n", "4136": "b7c8q", "4137": "b7c8r", "4138": "b7c8b", "4139": "b7c8n", "4140": "b7d8q", "4141": "b7d8r", "4142": "b7d8b", "4143": "b7d8n", "4144": "b7e8q", "4145": "b7e8r", "4146": "b7e8b", "4147": "b7e8n", "4148": "b7f8q", "4149": "b7f8r", "4150": "b7f8b", "4151": "b7f8n", "4152": "b7g8q", "4153": "b7g8r", "4154": "b7g8b", "4155": "b7g8n", "4156": "b7h8q", "4157": "b7h8r", "4158": "b7h8b", "4159": "b7h8n", "4160": "c7a8q", "4161": "c7a8r", "4162": "c7a8b", "4163": "c7a8n", "4164": "c7b8q", "4165": "c7b8r", "4166": "c7b8b", "4167": "c7b8n", "4168": "c7c8q", "4169": "c7c8r", "4170": "c7c8b", "4171": "c7c8n", "4172": "c7d8q", "4173": "c7d8r", "4174": "c7d8b", "4175": "c7d8n", "4176": "c7e8q", "4177": "c7e8r", "4178": "c7e8b", "4179": "c7e8n", "4180": "c7f8q", "4181": "c7f8r", "4182": "c7f8b", "4183": "c7f8n", "4184": "c7g8q", "4185": "c7g8r", "4186": "c7g8b", "4187": "c7g8n", "4188": "c7h8q", "4189": "c7h8r", "4190": "c7h8b", "4191": "c7h8n", "4192": "d7a8q", "4193": "d7a8r", "4194": "d7a8b", "4195": "d7a8n", "4196": "d7b8q", "4197": "d7b8r", "4198": "d7b8b", "4199": "d7b8n", "4200": "d7c8q", "4201": "d7c8r", "4202": "d7c8b", "4203": "d7c8n", "4204": "d7d8q", "4205": "d7d8r", "4206": "d7d8b", "4207": "d7d8n", "4208": "d7e8q", "4209": "d7e8r", "4210": "d7e8b", "4211": "d7e8n", "4212": "d7f8q", "4213": "d7f8r", "4214": "d7f8b", "4215": "d7f8n", "4216": "d7g8q", "4217": "d7g8r", "4218": "d7g8b", "4219": "d7g8n", "4220": "d7h8q", "4221": "d7h8r", "4222": "d7h8b", "4223": "d7h8n", "4224": "e7a8q", "4225": "e7a8r", "4226": "e7a8b", "4227": "e7a8n", "4228": "e7b8q", "4229": "e7b8r", "4230": "e7b8b", "4231": "e7b8n", "4232": "e7c8q", "4233": "e7c8r", "4234": "e7c8b", "4235": "e7c8n", "4236": "e7d8q", "4237": "e7d8r", "4238": "e7d8b", "4239": "e7d8n", "4240": "e7e8q", "4241": "e7e8r", "4242": "e7e8b", "4243": "e7e8n", "4244": "e7f8q", "4245": "e7f8r", "4246": "e7f8b", "4247": "e7f8n", "4248": "e7g8q", "4249": "e7g8r", "4250": "e7g8b", "4251": "e7g8n", "4252": "e7h8q", "4253": "e7h8r", "4254": "e7h8b", "4255": "e7h8n", "4256": "f7a8q", "4257": "f7a8r", "4258": "f7a8b", "4259": "f7a8n", "4260": "f7b8q", "4261": "f7b8r", "4262": "f7b8b", "4263": "f7b8n", "4264": "f7c8q", "4265": "f7c8r", "4266": "f7c8b", "4267": "f7c8n", "4268": "f7d8q", "4269": "f7d8r", "4270": "f7d8b", "4271": "f7d8n", "4272": "f7e8q", "4273": "f7e8r", "4274": "f7e8b", "4275": "f7e8n", "4276": "f7f8q", "4277": "f7f8r", "4278": "f7f8b", "4279": "f7f8n", "4280": "f7g8q", "4281": "f7g8r", "4282": "f7g8b", "4283": "f7g8n", "4284": "f7h8q", "4285": "f7h8r", "4286": "f7h8b", "4287": "f7h8n", "4288": "g7a8q", "4289": "g7a8r", "4290": "g7a8b", "4291": "g7a8n", "4292": "g7b8q", "4293": "g7b8r", "4294": "g7b8b", "4295": "g7b8n", "4296": "g7c8q", "4297": "g7c8r", "4298": "g7c8b", "4299": "g7c8n", "4300": "g7d8q", "4301": "g7d8r", "4302": "g7d8b", "4303": "g7d8n", "4304": "g7e8q", "4305": "g7e8r", "4306": "g7e8b", "4307": "g7e8n", "4308": "g7f8q", "4309": "g7f8r", "4310": "g7f8b", "4311": "g7f8n", "4312": "g7g8q", "4313": "g7g8r", "4314": "g7g8b", "4315": "g7g8n", "4316": "g7h8q", "4317": "g7h8r", "4318": "g7h8b", "4319": "g7h8n", "4320": "h7a8q", "4321": "h7a8r", "4322": "h7a8b", "4323": "h7a8n", "4324": "h7b8q", "4325": "h7b8r", "4326": "h7b8b", "4327": "h7b8n", "4328": "h7c8q", "4329": "h7c8r", "4330": "h7c8b", "4331": "h7c8n", "4332": "h7d8q", "4333": "h7d8r", "4334": "h7d8b", "4335": "h7d8n", "4336": "h7e8q", "4337": "h7e8r", "4338": "h7e8b", "4339": "h7e8n", "4340": "h7f8q", "4341": "h7f8r", "4342": "h7f8b", "4343": "h7f8n", "4344": "h7g8q", "4345": "h7g8r", "4346": "h7g8b", "4347": "h7g8n", "4348": "h7h8q", "4349": "h7h8r", "4350": "h7h8b", "4351": "h7h8n"}